Workbook

Sheet Summary
A1: OWASP ASVS 5.0 ? Compliance Tracker (GhostReport Phase 2 Sprint 1)
A5: Chapter | B5: Total Reqs | C5: L1 Total | D5: L1 Compliant | E5: L1 % | F5: L2 Total | G5: L2 Compliant | H5: L2 % | I5: L3 Total | J5: L3 Compliant | K5: L3 % | L5: Overall Compliant | M5: Overall %
A6: V1 – Encoding and Sanitization | B6: 30 | C6: 8 | D6: =COUNTIFS('V1 - Encoding and Sanitization'!$F$2:$F$36,"Compliant",'V1 - Encoding and Sanitization'!$E$2:$E$36,1) -> 3 | E6: =IF(C6=0,"",D6/C6) -> 0.375 | F6: 19 | G6: =COUNTIFS('V1 - Encoding and Sanitization'!$F$2:$F$36,"Compliant",'V1 - Encoding and Sanitization'!$E$2:$E$36,2) -> 1 | H6: =IF(F6=0,"",G6/F6) -> 0.052631579 | I6: 3 | J6: =COUNTIFS('V1 - Encoding and Sanitization'!$F$2:$F$36,"Compliant",'V1 - Encoding and Sanitization'!$E$2:$E$36,3) -> 0 | K6: =IF(I6=0,"",J6/I6) -> 0 | L6: =COUNTIF('V1 - Encoding and Sanitization'!$F$2:$F$36,"Compliant") -> 4 | M6: =IF(B6=0,"",L6/B6) -> 0.13333333
A7: V2 – Validation and Business Logic | B7: 13 | C7: 4 | D7: =COUNTIFS('V2 - Validation and Business Lo'!$F$2:$F$18,"Compliant",'V2 - Validation and Business Lo'!$E$2:$E$18,1) -> 4 | E7: =IF(C7=0,"",D7/C7) -> 1 | F7: 7 | G7: =COUNTIFS('V2 - Validation and Business Lo'!$F$2:$F$18,"Compliant",'V2 - Validation and Business Lo'!$E$2:$E$18,2) -> 0 | H7: =IF(F7=0,"",G7/F7) -> 0 | I7: 2 | J7: =COUNTIFS('V2 - Validation and Business Lo'!$F$2:$F$18,"Compliant",'V2 - Validation and Business Lo'!$E$2:$E$18,3) -> 0 | K7: =IF(I7=0,"",J7/I7) -> 0 | L7: =COUNTIF('V2 - Validation and Business Lo'!$F$2:$F$18,"Compliant") -> 4 | M7: =IF(B7=0,"",L7/B7) -> 0.30769231
A8: V3 – Web Frontend Security | B8: 31 | C8: 8 | D8: =COUNTIFS('V3 - Web Frontend Security'!$F$2:$F$39,"Compliant",'V3 - Web Frontend Security'!$E$2:$E$39,1) -> 3 | E8: =IF(C8=0,"",D8/C8) -> 0.375 | F8: 11 | G8: =COUNTIFS('V3 - Web Frontend Security'!$F$2:$F$39,"Compliant",'V3 - Web Frontend Security'!$E$2:$E$39,2) -> 1 | H8: =IF(F8=0,"",G8/F8) -> 0.090909091 | I8: 12 | J8: =COUNTIFS('V3 - Web Frontend Security'!$F$2:$F$39,"Compliant",'V3 - Web Frontend Security'!$E$2:$E$39,3) -> 0 | K8: =IF(I8=0,"",J8/I8) -> 0 | L8: =COUNTIF('V3 - Web Frontend Security'!$F$2:$F$39,"Compliant") -> 4 | M8: =IF(B8=0,"",L8/B8) -> 0.12903226
A9: V4 – API and Web Service | B9: 16 | C9: 2 | D9: =COUNTIFS('V4 - API and Web Service'!$F$2:$F$21,"Compliant",'V4 - API and Web Service'!$E$2:$E$21,1) -> 1 | E9: =IF(C9=0,"",D9/C9) -> 0.5 | F9: 8 | G9: =COUNTIFS('V4 - API and Web Service'!$F$2:$F$21,"Compliant",'V4 - API and Web Service'!$E$2:$E$21,2) -> 0 | H9: =IF(F9=0,"",G9/F9) -> 0 | I9: 6 | J9: =COUNTIFS('V4 - API and Web Service'!$F$2:$F$21,"Compliant",'V4 - API and Web Service'!$E$2:$E$21,3) -> 1 | K9: =IF(I9=0,"",J9/I9) -> 0.16666667 | L9: =COUNTIF('V4 - API and Web Service'!$F$2:$F$21,"Compliant") -> 2 | M9: =IF(B9=0,"",L9/B9) -> 0.125 | N9: Static Sprint 1 Snapshot | O9: Count
A10: V5 – File Handling | B10: 13 | C10: 4 | D10: =COUNTIFS('V5 - File Handling'!$F$2:$F$18,"Compliant",'V5 - File Handling'!$E$2:$E$18,1) -> 4 | E10: =IF(C10=0,"",D10/C10) -> 1 | F10: 5 | G10: =COUNTIFS('V5 - File Handling'!$F$2:$F$18,"Compliant",'V5 - File Handling'!$E$2:$E$18,2) -> 1 | H10: =IF(F10=0,"",G10/F10) -> 0.2 | I10: 4 | J10: =COUNTIFS('V5 - File Handling'!$F$2:$F$18,"Compliant",'V5 - File Handling'!$E$2:$E$18,3) -> 0 | K10: =IF(I10=0,"",J10/I10) -> 0 | L10: =COUNTIF('V5 - File Handling'!$F$2:$F$18,"Compliant") -> 5 | M10: =IF(B10=0,"",L10/B10) -> 0.38461538 | N10: Compliant | O10: 50
A11: V6 – Authentication | B11: 47 | C11: 13 | D11: =COUNTIFS('V6 - Authentication'!$F$2:$F$56,"Compliant",'V6 - Authentication'!$E$2:$E$56,1) -> 3 | E11: =IF(C11=0,"",D11/C11) -> 0.23076923 | F11: 22 | G11: =COUNTIFS('V6 - Authentication'!$F$2:$F$56,"Compliant",'V6 - Authentication'!$E$2:$E$56,2) -> 0 | H11: =IF(F11=0,"",G11/F11) -> 0 | I11: 12 | J11: =COUNTIFS('V6 - Authentication'!$F$2:$F$56,"Compliant",'V6 - Authentication'!$E$2:$E$56,3) -> 0 | K11: =IF(I11=0,"",J11/I11) -> 0 | L11: =COUNTIF('V6 - Authentication'!$F$2:$F$56,"Compliant") -> 3 | M11: =IF(B11=0,"",L11/B11) -> 0.063829787 | N11: In Progress | O11: 51
A12: V7 – Session Management | B12: 19 | C12: 6 | D12: =COUNTIFS('V7 - Session Management'!$F$2:$F$26,"Compliant",'V7 - Session Management'!$E$2:$E$26,1) -> 3 | E12: =IF(C12=0,"",D12/C12) -> 0.5 | F12: 12 | G12: =COUNTIFS('V7 - Session Management'!$F$2:$F$26,"Compliant",'V7 - Session Management'!$E$2:$E$26,2) -> 2 | H12: =IF(F12=0,"",G12/F12) -> 0.16666667 | I12: 1 | J12: =COUNTIFS('V7 - Session Management'!$F$2:$F$26,"Compliant",'V7 - Session Management'!$E$2:$E$26,3) -> 0 | K12: =IF(I12=0,"",J12/I12) -> 0 | L12: =COUNTIF('V7 - Session Management'!$F$2:$F$26,"Compliant") -> 5 | M12: =IF(B12=0,"",L12/B12) -> 0.26315789 | N12: Not Applicable | O12: 125
A13: V8 – Authorization | B13: 13 | C13: 4 | D13: =COUNTIFS('V8 - Authorization'!$F$2:$F$18,"Compliant",'V8 - Authorization'!$E$2:$E$18,1) -> 4 | E13: =IF(C13=0,"",D13/C13) -> 1 | F13: 3 | G13: =COUNTIFS('V8 - Authorization'!$F$2:$F$18,"Compliant",'V8 - Authorization'!$E$2:$E$18,2) -> 0 | H13: =IF(F13=0,"",G13/F13) -> 0 | I13: 6 | J13: =COUNTIFS('V8 - Authorization'!$F$2:$F$18,"Compliant",'V8 - Authorization'!$E$2:$E$18,3) -> 0 | K13: =IF(I13=0,"",J13/I13) -> 0 | L13: =COUNTIF('V8 - Authorization'!$F$2:$F$18,"Compliant") -> 4 | M13: =IF(B13=0,"",L13/B13) -> 0.30769231 | N13: Not Started | O13: 119
A14: V9 – Self-contained Tokens | B14: 7 | C14: 4 | D14: =COUNTIFS('V9 - Self-contained Tokens'!$F$2:$F$10,"Compliant",'V9 - Self-contained Tokens'!$E$2:$E$10,1) -> 4 | E14: =IF(C14=0,"",D14/C14) -> 1 | F14: 3 | G14: =COUNTIFS('V9 - Self-contained Tokens'!$F$2:$F$10,"Compliant",'V9 - Self-contained Tokens'!$E$2:$E$10,2) -> 0 | H14: =IF(F14=0,"",G14/F14) -> 0 | I14: 0 | J14: N/A | K14: N/A | L14: =COUNTIF('V9 - Self-contained Tokens'!$F$2:$F$10,"Compliant") -> 4 | M14: =IF(B14=0,"",L14/B14) -> 0.57142857 | N14: L1 Compliant | O14: 33 / 70
A15: V10 – OAuth and OIDC | B15: 36 | C15: 5 | D15: =COUNTIFS('V10 - OAuth and OIDC'!$F$2:$F$44,"Compliant",'V10 - OAuth and OIDC'!$E$2:$E$44,1) -> 0 | E15: =IF(C15=0,"",D15/C15) -> 0 | F15: 24 | G15: =COUNTIFS('V10 - OAuth and OIDC'!$F$2:$F$44,"Compliant",'V10 - OAuth and OIDC'!$E$2:$E$44,2) -> 0 | H15: =IF(F15=0,"",G15/F15) -> 0 | I15: 7 | J15: =COUNTIFS('V10 - OAuth and OIDC'!$F$2:$F$44,"Compliant",'V10 - OAuth and OIDC'!$E$2:$E$44,3) -> 0 | K15: =IF(I15=0,"",J15/I15) -> 0 | L15: =COUNTIF('V10 - OAuth and OIDC'!$F$2:$F$44,"Compliant") -> 0 | M15: =IF(B15=0,"",L15/B15) -> 0 | N15: L2 Compliant | O15: 15 / 183
A16: V11 – Cryptography | B16: 24 | C16: 3 | D16: =COUNTIFS('V11 - Cryptography'!$F$2:$F$32,"Compliant",'V11 - Cryptography'!$E$2:$E$32,1) -> 2 | E16: =IF(C16=0,"",D16/C16) -> 0.66666667 | F16: 11 | G16: =COUNTIFS('V11 - Cryptography'!$F$2:$F$32,"Compliant",'V11 - Cryptography'!$E$2:$E$32,2) -> 1 | H16: =IF(F16=0,"",G16/F16) -> 0.090909091 | I16: 10 | J16: =COUNTIFS('V11 - Cryptography'!$F$2:$F$32,"Compliant",'V11 - Cryptography'!$E$2:$E$32,3) -> 0 | K16: =IF(I16=0,"",J16/I16) -> 0 | L16: =COUNTIF('V11 - Cryptography'!$F$2:$F$32,"Compliant") -> 3 | M16: =IF(B16=0,"",L16/B16) -> 0.125 | N16: L3 Compliant | O16: 2 / 92
A17: V12 – Secure Communication | B17: 12 | C17: 3 | D17: =COUNTIFS('V12 - Secure Communication'!$F$2:$F$16,"Compliant",'V12 - Secure Communication'!$E$2:$E$16,1) -> 0 | E17: =IF(C17=0,"",D17/C17) -> 0 | F17: 6 | G17: =COUNTIFS('V12 - Secure Communication'!$F$2:$F$16,"Compliant",'V12 - Secure Communication'!$E$2:$E$16,2) -> 0 | H17: =IF(F17=0,"",G17/F17) -> 0 | I17: 3 | J17: =COUNTIFS('V12 - Secure Communication'!$F$2:$F$16,"Compliant",'V12 - Secure Communication'!$E$2:$E$16,3) -> 0 | K17: =IF(I17=0,"",J17/I17) -> 0 | L17: =COUNTIF('V12 - Secure Communication'!$F$2:$F$16,"Compliant") -> 0 | M17: =IF(B17=0,"",L17/B17) -> 0
A18: V13 – Configuration | B18: 21 | C18: 1 | D18: =COUNTIFS('V13 - Configuration'!$F$2:$F$26,"Compliant",'V13 - Configuration'!$E$2:$E$26,1) -> 0 | E18: =IF(C18=0,"",D18/C18) -> 0 | F18: 12 | G18: =COUNTIFS('V13 - Configuration'!$F$2:$F$26,"Compliant",'V13 - Configuration'!$E$2:$E$26,2) -> 2 | H18: =IF(F18=0,"",G18/F18) -> 0.16666667 | I18: 8 | J18: =COUNTIFS('V13 - Configuration'!$F$2:$F$26,"Compliant",'V13 - Configuration'!$E$2:$E$26,3) -> 0 | K18: =IF(I18=0,"",J18/I18) -> 0 | L18: =COUNTIF('V13 - Configuration'!$F$2:$F$26,"Compliant") -> 2 | M18: =IF(B18=0,"",L18/B18) -> 0.095238095
A19: V14 – Data Protection | B19: 13 | C19: 2 | D19: =COUNTIFS('V14 - Data Protection'!$F$2:$F$17,"Compliant",'V14 - Data Protection'!$E$2:$E$17,1) -> 1 | E19: =IF(C19=0,"",D19/C19) -> 0.5 | F19: 7 | G19: =COUNTIFS('V14 - Data Protection'!$F$2:$F$17,"Compliant",'V14 - Data Protection'!$E$2:$E$17,2) -> 0 | H19: =IF(F19=0,"",G19/F19) -> 0 | I19: 4 | J19: =COUNTIFS('V14 - Data Protection'!$F$2:$F$17,"Compliant",'V14 - Data Protection'!$E$2:$E$17,3) -> 0 | K19: =IF(I19=0,"",J19/I19) -> 0 | L19: =COUNTIF('V14 - Data Protection'!$F$2:$F$17,"Compliant") -> 1 | M19: =IF(B19=0,"",L19/B19) -> 0.076923077
A20: V15 – Secure Coding and Architecture | B20: 21 | C20: 3 | D20: =COUNTIFS('V15 - Secure Coding and Archite'!$F$2:$F$26,"Compliant",'V15 - Secure Coding and Archite'!$E$2:$E$26,1) -> 1 | E20: =IF(C20=0,"",D20/C20) -> 0.33333333 | F20: 10 | G20: =COUNTIFS('V15 - Secure Coding and Archite'!$F$2:$F$26,"Compliant",'V15 - Secure Coding and Archite'!$E$2:$E$26,2) -> 1 | H20: =IF(F20=0,"",G20/F20) -> 0.1 | I20: 8 | J20: =COUNTIFS('V15 - Secure Coding and Archite'!$F$2:$F$26,"Compliant",'V15 - Secure Coding and Archite'!$E$2:$E$26,3) -> 0 | K20: =IF(I20=0,"",J20/I20) -> 0 | L20: =COUNTIF('V15 - Secure Coding and Archite'!$F$2:$F$26,"Compliant") -> 2 | M20: =IF(B20=0,"",L20/B20) -> 0.095238095
A21: V16 – Security Logging and Error Handling | B21: 17 | C21: 0 | D21: N/A | E21: N/A | F21: 16 | G21: =COUNTIFS('V16 - Security Logging and Erro'!$F$2:$F$23,"Compliant",'V16 - Security Logging and Erro'!$E$2:$E$23,2) -> 6 | H21: =IF(F21=0,"",G21/F21) -> 0.375 | I21: 1 | J21: =COUNTIFS('V16 - Security Logging and Erro'!$F$2:$F$23,"Compliant",'V16 - Security Logging and Erro'!$E$2:$E$23,3) -> 1 | K21: =IF(I21=0,"",J21/I21) -> 1 | L21: =COUNTIF('V16 - Security Logging and Erro'!$F$2:$F$23,"Compliant") -> 7 | M21: =IF(B21=0,"",L21/B21) -> 0.41176471
A22: V17 – WebRTC | B22: 12 | C22: 0 | D22: N/A | E22: N/A | F22: 7 | G22: =COUNTIFS('V17 - WebRTC'!$F$2:$F$16,"Compliant",'V17 - WebRTC'!$E$2:$E$16,2) -> 0 | H22: =IF(F22=0,"",G22/F22) -> 0 | I22: 5 | J22: =COUNTIFS('V17 - WebRTC'!$F$2:$F$16,"Compliant",'V17 - WebRTC'!$E$2:$E$16,3) -> 0 | K22: =IF(I22=0,"",J22/I22) -> 0 | L22: =COUNTIF('V17 - WebRTC'!$F$2:$F$16,"Compliant") -> 0 | M22: =IF(B22=0,"",L22/B22) -> 0
A23: TOTAL | B23: =SUM(B6:B22) -> 345 | C23: =SUM(C6:C22) -> 70 | D23: =SUM(D6:D22) -> 33 | E23: =IFERROR(AVERAGE(E6:E22),"") -> 0.49871795 | F23: =SUM(F6:F22) -> 183 | G23: =SUM(G6:G22) -> 15 | H23: =IFERROR(AVERAGE(H6:H22),"") -> 0.073104888 | I23: =SUM(I6:I22) -> 92 | J23: =SUM(J6:J22) -> 2 | K23: =IFERROR(AVERAGE(K6:K22),"") -> 0.072916667 | L23: =SUM(L6:L22) -> 50 | M23: =IFERROR(AVERAGE(M6:M22),"") -> 0.18176152

Sheet Sprint 1 Evidence
A1: Area | B1: ASVS Mapping | C1: Implemented Control | D1: Evidence | E1: Residual Risk / Next Step
A2: Authentication | B2: V6, V7, V9 | C2: JWT Bearer stateless authentication, HS256/HMAC-SHA256 validation, BCrypt password hashing, 3600s configurable expiration. | D2: AuthService.java; JwtService.java; JwtAuthenticationFilter.java; SecurityConfig.java; CreateUserRequest.java | E2: No MFA and no login-specific rate limiting yet.
A3: Authorization | B3: V8 | C3: Central RBAC rules for ADMIN, ANALYST and AUDITOR plus service-level analyst ownership checks. | D3: SecurityConfig.java; ReportService.java; CasePackageService.java; AdminAuthorizationTest; AnalystCaseOwnershipTest; RbacAuthorizationMatrixTest | E3: Full field-level matrix can be expanded.
A4: Input validation | B4: V1, V2 | C4: Jakarta Bean Validation, domain primitives, server-side validation and controlled error handling. | D4: DTO package; SafeFilename.java; TrackingCode.java; ReportDescription.java; GlobalExceptionHandler.java | E4: More negative tests can be added for controllers/errors.
A5: File handling | B5: V5 | C5: 10 MB file limit, MIME/extension allowlist, magic-byte validation, UUID stored names and path normalization. | D5: FileStorageService.java; ReportControllerAttachmentUploadTest; FileStorageServiceTest; SafeFilenameSecurityTest | E5: No real antimalware scanning or global quota.
A6: Tracking code and anonymity | B6: V2, V14, V16 | C6: High-entropy tracking code, hash storage, generic verification behavior, logging minimization. | D6: TrackingCode.java; ReportService.java; TrackingCodeEnumerationTest; AnonymousDataLoggingTest | E6: Advanced abuse detection/CAPTCHA not implemented.
A7: Audit and monitoring | B7: V16 | C7: Audit logs and security alerts for critical operations and suspicious behavior. | D7: AuditLogService.java; SecurityMonitoringService.java; AuditController.java | E7: Logs are not append-only/tamper-proof and not exported to external SIEM.
A8: Evidence and backups | B8: V5, V11, V14, V16 | C8: Evidence packages and backups include manifests and SHA-256 integrity hashes; restore staging avoids direct overwrite. | D8: CasePackageService.java; BackupService.java; BackupServiceIntegrationTest; CasePackageServiceIntegrationTest | E8: No encryption/signature/retention policy yet.
A9: DevSecOps pipeline | B9: V13, V15 | C9: CI tests, JaCoCo, SpotBugs SAST, Dependency-Check SCA, Gitleaks and ZAP baseline DAST with artifacts. | D9: .github/workflows/*.yml; pom.xml; pipeline artifacts | E9: Policy gates and authenticated DAST are future work.

Sheet Assessment Notes
A1: Assessment methodology
A2: Updated for GhostReport Phase 2 Sprint 1 using implemented code, automated tests, GitHub Actions workflows and the Sprint 1 report.
A4: Scope
A5: Spring Boot backend, static HTML/CSS/JavaScript frontend, PostgreSQL persistence, local controlled file storage, backups, JWT backoffice authentication, RBAC, analyst ownership, audit logs, security alerts, SAST/SCA/DAST/secret scanning workflows and automated tests.
A7: Status logic
A8: Compliant = implemented and supported by code/tests/workflows for the current Sprint 1 scope.
A9: In Progress = partially implemented or documented, but with known limitations or future hardening still required.
A10: Not Applicable = outside current GhostReport scope.
A11: Not Started = not implemented or not evidenced in Sprint 1.
A13: Important limitations kept explicit
A14: No real antimalware scanning, no global storage quotas, no MFA, no append-only/tamper-proof audit log store, no distributed rate limiting, no authenticated ZAP scan, no formal SBOM gate.

Sheet V1 - Encoding and Sanitization
A1: Section ID | B1: Section Name | C1: Req ID | D1: Description | E1: Level | F1: Status | G1: Observations | H1: Reference / Link
A2: V1.1 | B2: Encoding and Sanitization Architecture
A3: V1.1 | B3: Encoding and Sanitization Architecture | C3: V1.1.1 | D3: Verify that input is decoded or unescaped into a canonical form only once, it is only decoded when encoded data in that form is expected, and that this is done before processing the input further, for example it is not performed after input validation or sanitization. | E3: 2 | F3: Compliant | G3: Path and filename inputs are canonicalized/normalized before use. FileStorageService resolves paths with toAbsolutePath().normalize() and verifies they remain under the configured base directory. | H3: Sprint 1 report ?6; FileStorageService.java; SafeFilename.java; FileStorageServiceTest; SafeFilenameSecurityTest
A4: V1.1 | B4: Encoding and Sanitization Architecture | C4: V1.1.2 | D4: Verify that the application performs output encoding and escaping either as a final step before being used by the interpreter for which it is intended or by the interpreter itself. | E4: 2 | F4: In Progress | G4: Safe serialization/escaping for responses and downstream interpreters should be confirmed in implementation. | H4: DESOFS Phase 1: input validation in mitigations §13 and tests §14
A5: V1.2 | B5: Injection Prevention
A6: V1.2 | B6: Injection Prevention | C6: V1.2.1 | D6: Verify that output encoding for an HTTP response, HTML document, or XML document is relevant for the context required, such as encoding the relevant characters for HTML elements, HTML attributes, HTML comments, CSS, or HTTP header fields, to avoid changing the message or document structure. | E6: 1 | F6: Not Applicable | G6: Not applicable in the current system design. | H6: N/A – not in current system scope
A7: V1.2 | B7: Injection Prevention | C7: V1.2.2 | D7: Verify that when dynamically building URLs, untrusted data is encoded according to its context (e.g., URL encoding or base64url encoding for query or path parameters). Ensure that only safe URL protocols are permitted (e.g., disallow javascript: or data:). | E7: 1 | F7: Not Applicable | G7: Not applicable in the current system design. | H7: N/A – not in current system scope
A8: V1.2 | B8: Injection Prevention | C8: V1.2.3 | D8: Verify that output encoding or escaping is used when dynamically building JavaScript content (including JSON), to avoid changing the message or document structure (to avoid JavaScript and JSON injection). | E8: 1 | F8: In Progress | G8: Backend JSON responses are generated through Spring/Jackson and validation errors are structured by GlobalExceptionHandler. Further frontend-specific output encoding review remains future hardening. | H8: GlobalExceptionHandler.java; Sprint 1 report ?8
A9: V1.2 | B9: Injection Prevention | C9: V1.2.4 | D9: Verify that data selection or database queries (e.g., SQL, HQL, NoSQL, Cypher) use parameterized queries, ORMs, entity frameworks, or are otherwise protected from SQL Injection and other database injection attacks. This is also relevant when writing stored procedures. | E9: 1 | F9: Compliant | G9: Application data access uses Spring Data JPA repositories and framework-managed query binding. No user-controlled SQL string concatenation is used for business endpoints. | H9: Repository interfaces; service layer; Sprint 1 report ?2
A10: V1.2 | B10: Injection Prevention | C10: V1.2.5 | D10: Verify that the application protects against OS command injection and that operating system calls use parameterized OS queries or use contextual command line output encoding. | E10: 1 | F10: Compliant | G10: No application feature invokes operating system shell commands with user-controlled input. File operations use Java NIO APIs with controlled paths. | H10: FileStorageService.java; BackupService.java
A11: V1.2 | B11: Injection Prevention | C11: V1.2.6 | D11: Verify that the application protects against LDAP injection vulnerabilities, or that specific security controls to prevent LDAP injection have been implemented. | E11: 2 | F11: Not Applicable | G11: Not applicable in the current system design. | H11: N/A – not in current system scope
A12: V1.2 | B12: Injection Prevention | C12: V1.2.7 | D12: Verify that the application is protected against XPath injection attacks by using query parameterization or precompiled queries. | E12: 2 | F12: Not Applicable | G12: Not applicable in the current system design. | H12: N/A – not in current system scope
A13: V1.2 | B13: Injection Prevention | C13: V1.2.8 | D13: Verify that LaTeX processors are configured securely (such as not using the "--shell-escape" flag) and an allowlist of commands is used to prevent LaTeX injection attacks. | E13: 2 | F13: Not Applicable | G13: Not applicable in the current system design. | H13: N/A – not in current system scope
A14: V1.2 | B14: Injection Prevention | C14: V1.2.9 | D14: Verify that the application escapes special characters in regular expressions (typically using a backslash) to prevent them from being misinterpreted as metacharacters. | E14: 2 | F14: In Progress | G14: Regex safety for validation patterns should be reviewed during implementation. | H14: DESOFS Phase 1: input validation in mitigations §13 and tests §14
A15: V1.2 | B15: Injection Prevention | C15: V1.2.10 | D15: Verify that the application is protected against CSV and Formula Injection. The application must follow the escaping rules defined in RFC 4180 sections 2.6 and 2.7 when exporting CSV content. Additionally, when exporting to CSV or other spreadsheet formats (such as XLS, XLSX, or ODF), special characters (including '=', '+', '-', '@', '\t' (tab), and '\0' (null character)) must be escaped with a single quote if they appear as the first character in a field value. | E15: 3 | F15: Not Started | G15: Spreadsheet/CSV export handling is not yet specified; escape dangerous leading characters if exports are added. | H15: Project.pdf: backend API, 3 roles, OS/file ops, ASVS deliverable
A16: V1.3 | B16: Sanitization
A17: V1.3 | B17: Sanitization | C17: V1.3.1 | D17: Verify that all untrusted HTML input from WYSIWYG editors or similar is sanitized using a well-known and secure HTML sanitization library or framework feature. | E17: 1 | F17: Not Applicable | G17: Not applicable in the current system design. | H17: N/A – not in current system scope
A18: V1.3 | B18: Sanitization | C18: V1.3.2 | D18: Verify that the application avoids the use of eval() or other dynamic code execution features such as Spring Expression Language (SpEL). Where there is no alternative, any user input being included must be sanitized before being executed. | E18: 1 | F18: Compliant | G18: No dynamic code execution feature such as eval(), expression evaluation, or user-controlled script execution is used in the backend implementation. | H18: Code review Sprint 1; SpotBugs SAST report
A19: V1.3 | B19: Sanitization | C19: V1.3.3 | D19: Verify that data being passed to a potentially dangerous context is sanitized beforehand to enforce safety measures, such as only allowing characters which are safe for this context and trimming input which is too long. | E19: 2 | F19: In Progress | G19: User input is validated in the design (RS4, RS5), but context-specific sanitization (e.g., for file paths, database queries, or outputs) is not explicitly defined. | H19: DESOFS Phase 1: input validation in mitigations §13 and tests §14
A20: V1.3 | B20: Sanitization | C20: V1.3.4 | D20: Verify that user-supplied Scalable Vector Graphics (SVG) scriptable content is validated or sanitized to contain only tags and attributes (such as draw graphics) that are safe for the application, e.g., do not contain scripts and foreignObject. | E20: 2 | F20: Not Applicable | G20: Not applicable in the current system design. | H20: N/A – not in current system scope
A21: V1.3 | B21: Sanitization | C21: V1.3.5 | D21: Verify that the application sanitizes or disables user-supplied scriptable or expression template language content, such as Markdown, CSS or XSL stylesheets, BBCode, or similar. | E21: 2 | F21: Not Applicable | G21: Not applicable in the current system design. | H21: N/A – not in current system scope
A22: V1.3 | B22: Sanitization | C22: V1.3.6 | D22: Verify that the application protects against Server-side Request Forgery (SSRF) attacks, by validating untrusted data against an allowlist of protocols, domains, paths and ports and sanitizing potentially dangerous characters before using the data to call another service. | E22: 2 | F22: In Progress | G22: The system processes user input but does not define restrictions on external resource access (e.g., URLs, APIs), which may lead to SSRF risks if implemented without proper validation. | H22: DESOFS Phase 1: input validation in mitigations §13 and tests §14
A23: V1.3 | B23: Sanitization | C23: V1.3.7 | D23: Verify that the application protects against template injection attacks by not allowing templates to be built based on untrusted input. Where there is no alternative, any untrusted input being included dynamically during template creation must be sanitized or strictly validated. | E23: 2 | F23: In Progress | G23: No template engine is explicitly defined in the design, but if dynamic content rendering is introduced, input validation and strict separation between templates and user data must be enforced. | H23: DESOFS Phase 1: input validation in mitigations §13 and tests §14
A24: V1.3 | B24: Sanitization | C24: V1.3.8 | D24: Verify that the application appropriately sanitizes untrusted input before use in Java Naming and Directory Interface (JNDI) queries and that JNDI is configured securely to prevent JNDI injection attacks. | E24: 2 | F24: Not Applicable | G24: Not applicable in the current system design. | H24: N/A – not in current system scope
A25: V1.3 | B25: Sanitization | C25: V1.3.9 | D25: Verify that the application sanitizes content before it is sent to memcache to prevent injection attacks. | E25: 2 | F25: Not Applicable | G25: Not applicable in the current system design. | H25: N/A – not in current system scope
A26: V1.3 | B26: Sanitization | C26: V1.3.10 | D26: Verify that format strings which might resolve in an unexpected or malicious way when used are sanitized before being processed. | E26: 2 | F26: In Progress | G26: Input validation is defined, but no explicit handling of format string risks is described in the design. | H26: DESOFS Phase 1: input validation in mitigations §13 and tests §14
A27: V1.3 | B27: Sanitization | C27: V1.3.11 | D27: Verify that the application sanitizes user input before passing to mail systems to protect against SMTP or IMAP injection. | E27: 2 | F27: Not Applicable | G27: Not applicable in the current system design. | H27: N/A – not in current system scope
A28: V1.3 | B28: Sanitization | C28: V1.3.12 | D28: Verify that regular expressions are free from elements causing exponential backtracking, and ensure untrusted input is sanitized to mitigate ReDoS or Runaway Regex attacks. | E28: 3 | F28: In Progress | G28: Input validation is required, but no constraints on regex complexity or protections against ReDoS attacks are defined in the design. | H28: DESOFS Phase 1: input validation in mitigations §13 and tests §14
A29: V1.4 | B29: Memory, String, and Unmanaged Code
A30: V1.4 | B30: Memory, String, and Unmanaged Code | C30: V1.4.1 | D30: Verify that the application uses memory-safe string, safer memory copy and pointer arithmetic to detect or prevent stack, buffer, or heap overflows. | E30: 2 | F30: Not Applicable | G30: Not applicable in the current system design. | H30: N/A – not in current system scope
A31: V1.4 | B31: Memory, String, and Unmanaged Code | C31: V1.4.2 | D31: Verify that sign, range, and input validation techniques are used to prevent integer overflows. | E31: 2 | F31: Not Applicable | G31: Not applicable in the current system design. | H31: N/A – not in current system scope
A32: V1.4 | B32: Memory, String, and Unmanaged Code | C32: V1.4.3 | D32: Verify that dynamically allocated memory and resources are released, and that references or pointers to freed memory are removed or set to null to prevent dangling pointers and use-after-free vulnerabilities. | E32: 2 | F32: Not Applicable | G32: Not applicable in the current system design. | H32: N/A – not in current system scope
A33: V1.5 | B33: Safe Deserialization
A34: V1.5 | B34: Safe Deserialization | C34: V1.5.1 | D34: Verify that the application configures XML parsers to use a restrictive configuration and that unsafe features such as resolving external entities are disabled to prevent XML eXternal Entity (XXE) attacks. | E34: 1 | F34: Not Applicable | G34: The current Sprint 1 implementation does not parse user-supplied XML documents. | H34: Current implementation scope
A35: V1.5 | B35: Safe Deserialization | C35: V1.5.2 | D35: Verify that deserialization of untrusted data enforces safe input handling, such as using an allowlist of object types or restricting client-defined object types, to prevent deserialization attacks. Deserialization mechanisms that are explicitly defined as insecure must not be used with untrusted input. | E35: 2 | F35: Not Started | G35: The design does not specify secure parser configurations or restrictions for deserialization of untrusted data. | H35: DESOFS Phase 1: input validation in mitigations §13 and tests §14
A36: V1.5 | B36: Safe Deserialization | C36: V1.5.3 | D36: Verify that different parsers used in the application for the same data type (e.g., JSON parsers, XML parsers, URL parsers), perform parsing in a consistent way and use the same character encoding mechanism to avoid issues such as JSON Interoperability vulnerabilities or different URI or file parsing behavior being exploited in Remote File Inclusion (RFI) or Server-side Request Forgery (SSRF) attacks. | E36: 3 | F36: Not Started | G36: The design does not specify secure parser configurations or restrictions for deserialization of untrusted data. | H36: DESOFS Phase 1: input validation in mitigations §13 and tests §14

Sheet V2 - Validation and Business Lo
A1: Section ID | B1: Section Name | C1: Req ID | D1: Description | E1: Level | F1: Status | G1: Observations | H1: Reference / Link
A2: V2.1 | B2: Validation and Business Logic Documentation
A3: V2.1 | B3: Validation and Business Logic Documentation | C3: V2.1.1 | D3: Verify that the application's documentation defines input validation rules for how to check the validity of data items against an expected structure. This could be common data formats such as credit card numbers, email addresses, telephone numbers, or it could be an internal data format. | E3: 1 | F3: Compliant | G3: Sprint 1 documents validation rules for DTOs, tracking codes, filenames, MIME types, extensions, file size and business states. | H3: Sprint 1 report ?6, ?7, ?13; DTO classes; FileStorageService.java
A4: V2.1 | B4: Validation and Business Logic Documentation | C4: V2.1.2 | D4: Verify that the application's documentation defines how to validate the logical and contextual consistency of combined data items, such as checking that suburb and ZIP code match. | E4: 2 | F4: In Progress | G4: Contextual rules are implemented for analyst ownership, closed-case handling, evidence packages and backups, but a full business rule catalogue is not yet complete. | H4: ReportService.java; CasePackageService.java; AnalystCaseOwnershipTest; ClosedCaseSecurityTest
A5: V2.1 | B5: Validation and Business Logic Documentation | C5: V2.1.3 | D5: Verify that expectations for business logic limits and validations are documented, including both per-user and globally across the application. | E5: 2 | F5: In Progress | G5: Upload size limits and rate limits are implemented. Global storage quotas and distributed rate limiting remain future work. | H5: RateLimiterService.java; RateLimitProperties.java; FileStorageService.java; Sprint 1 report ?7
A6: V2.2 | B6: Input Validation
A7: V2.2 | B7: Input Validation | C7: V2.2.1 | D7: Verify that input is validated to enforce business or functional expectations for that input. This should either use positive validation against an allow list of values, patterns, and ranges, or be based on comparing the input to an expected structure and logical limits according to predefined rules. For L1, this can focus on input which is used to make specific business or security decisions. For L2 and up, this should apply to all input. | E7: 1 | F7: Compliant | G7: Security-sensitive inputs are validated server-side using Jakarta Bean Validation, domain primitives and service-level checks. | H7: DTO package; TrackingCode.java; SafeFilename.java; ReportDescription.java; FileStorageServiceTest
A8: V2.2 | B8: Input Validation | C8: V2.2.2 | D8: Verify that the application is designed to enforce input validation at a trusted service layer. While client-side validation improves usability and should be encouraged, it must not be relied upon as a security control. | E8: 1 | F8: Compliant | G8: Validation and authorization are enforced in the trusted Spring backend rather than relying on client-side JavaScript. | H8: Controller/service layer; SecurityConfig.java
A9: V2.2 | B9: Input Validation | C9: V2.2.3 | D9: Verify that the application ensures that combinations of related data items are reasonable according to the pre-defined rules. | E9: 2 | F9: In Progress | G9: Cross-field and business-context validation rules are not explicitly defined in the design. | H9: DESOFS Phase 1: input validation in mitigations §11 and tests §12
A10: V2.3 | B10: Business Logic Security
A11: V2.3 | B11: Business Logic Security | C11: V2.3.1 | D11: Verify that the application will only process business logic flows for the same user in the expected sequential step order and without skipping steps. | E11: 1 | F11: Compliant | G11: Main flows enforce expected sequence and state checks, including tracking-code verification, closed-case restrictions and evidence package generation only for closed cases. | H11: PublicReportFlowIntegrationTest; ClosedCaseSecurityTest; CasePackageServiceIntegrationTest
A12: V2.3 | B12: Business Logic Security | C12: V2.3.2 | D12: Verify that business logic limits are implemented per the application's documentation to avoid business logic flaws being exploited. | E12: 2 | F12: In Progress | G12: Documented limits/quotas/rate limiting are part of the threat mitigations. | H12: DESOFS Phase 1: DFD/trust boundaries §9; STRIDE §10; mitigations §11
A13: V2.3 | B13: Business Logic Security | C13: V2.3.3 | D13: Verify that transactions are being used at the business logic level such that either a business logic operation succeeds in its entirety or it is rolled back to the previous correct state. | E13: 2 | F13: Not Started | G13: Transactional rollback behavior for report/file/document creation should be specified during implementation. | H13: DESOFS Phase 1: Project design (no explicit transaction handling defined)
A14: V2.3 | B14: Business Logic Security | C14: V2.3.4 | D14: Verify that business logic level locking mechanisms are used to ensure that limited quantity resources (such as theater seats or delivery slots) cannot be double-booked by manipulating the application's logic. | E14: 2 | F14: Not Applicable | G14: Not applicable in the current system design. | H14: N/A – not in current system scope
A15: V2.3 | B15: Business Logic Security | C15: V2.3.5 | D15: Verify that high-value business logic flows require multi-user approval to prevent unauthorized or accidental actions. This could include but is not limited to large monetary transfers, contract approvals, access to classified information, or safety overrides in manufacturing. | E15: 3 | F15: Not Applicable | G15: Not applicable in the current system design. | H15: N/A – not in current system scope
A16: V2.4 | B16: Anti-automation
A17: V2.4 | B17: Anti-automation | C17: V2.4.1 | D17: Verify that anti-automation controls are in place to protect against excessive calls to application functions that could lead to data exfiltration, garbage-data creation, quota exhaustion, rate-limit breaches, denial-of-service, or overuse of costly resources. | E17: 2 | F17: In Progress | G17: Anti-automation and rate limiting are explicit mitigations for spam, brute force, and DoS. | H17: DESOFS Phase 1: DFD/trust boundaries §9; STRIDE §10; mitigations §11
A18: V2.4 | B18: Anti-automation | C18: V2.4.2 | D18: Verify that business logic flows require realistic human timing, preventing excessively rapid transaction submissions. | E18: 3 | F18: Not Started | G18: Human-timing defenses may help abuse resistance but are not yet specified. | H18: DESOFS Phase 1: DFD/trust boundaries §9; STRIDE §10; mitigations §11

Sheet V3 - Web Frontend Security
A1: Section ID | B1: Section Name | C1: Req ID | D1: Description | E1: Level | F1: Status | G1: Observations | H1: Reference / Link
A2: V3.1 | B2: Web Frontend Security Documentation
A3: V3.1 | B3: Web Frontend Security Documentation | C3: V3.1.1 | D3: Verify that application documentation states the expected security features that browsers using the application must support (such as HTTPS, HTTP Strict Transport Security (HSTS), Content Security Policy (CSP), and other relevant HTTP security mechanisms). It must also define how the application must behave when some of these features are not available (such as warning the user or blocking access). | E3: 3 | F3: Not Started | G3: Backend project may later have a browser client; frontend/browser controls are mostly still to be specified. | H3: Project.pdf: backend API, 3 roles, OS/file ops, ASVS deliverable
A4: V3.2 | B4: Unintended Content Interpretation
A5: V3.2 | B5: Unintended Content Interpretation | C5: V3.2.1 | D5: Verify that security controls are in place to prevent browsers from rendering content or functionality in HTTP responses in an incorrect context (e.g., when an API, a user-uploaded file or other resource is requested directly). Possible controls could include: not serving the content unless HTTP request header fields (such as Sec-Fetch-\*) indicate it is the correct context, using the sandbox directive of the Content-Security-Policy header field or using the attachment disposition type in the Content-Disposition header field. | E5: 1 | F5: In Progress | G5: Security headers are configured and uploaded files are stored outside the static web root. Additional download hardening and browser isolation policies remain future work. | H5: SecurityConfig.java; FileStorageService.java; ZAP report
A6: V3.2 | B6: Unintended Content Interpretation | C6: V3.2.2 | D6: Verify that content intended to be displayed as text, rather than rendered as HTML, is handled using safe rendering functions (such as createTextNode or textContent) to prevent unintended execution of content such as HTML or JavaScript. | E6: 1 | F6: Not Applicable | G6: Not applicable in the current backend-only design; this would only be relevant if a browser-based client were introduced. | H6: N/A – frontend/browser functionality not in current system scope
A7: V3.2 | B7: Unintended Content Interpretation | C7: V3.2.3 | D7: Verify that the application avoids DOM clobbering when using client-side JavaScript by employing explicit variable declarations, performing strict type checking, avoiding storing global variables on the document object, and implementing namespace isolation. | E7: 3 | F7: Not Applicable | G7: Not applicable in the current backend-only design; this would only be relevant if a browser-based client were introduced. | H7: N/A – frontend/browser functionality not in current system scope
A8: V3.3 | B8: Cookie Setup
A9: V3.3 | B9: Cookie Setup | C9: V3.3.1 | D9: Verify that cookies have the 'Secure' attribute set, and if the '\__Host-' prefix is not used for the cookie name, the '__Secure-' prefix must be used for the cookie name. | E9: 1 | F9: Compliant | G9: Secure and HttpOnly cookies are explicitly required for authenticated staff sessions. | H9: DESOFS Phase 1: §5.1 RS1-RS3; AC5/AC8/AC11; STRIDE P5/P6; §12 tests
A10: V3.3 | B10: Cookie Setup | C10: V3.3.2 | D10: Verify that each cookie's 'SameSite' attribute value is set according to the purpose of the cookie, to limit exposure to user interface redress attacks and browser-based request forgery attacks, commonly known as cross-site request forgery (CSRF). | E10: 2 | F10: Not Started | G10: Cookies are in scope for staff sessions, but SameSite/prefix details are not yet specified. | H10: DESOFS Phase 1: §5.1 RS1-RS3; AC5/AC8/AC11; STRIDE P5/P6; §12 tests
A11: V3.3 | B11: Cookie Setup | C11: V3.3.3 | D11: Verify that cookies have the '__Host-' prefix for the cookie name unless they are explicitly designed to be shared with other hosts. | E11: 2 | F11: Not Started | G11: Cookies are in scope for staff sessions, but SameSite/prefix details are not yet specified. | H11: DESOFS Phase 1: §5.1 RS1-RS3; AC5/AC8/AC11; STRIDE P5/P6; §12 tests
A12: V3.3 | B12: Cookie Setup | C12: V3.3.4 | D12: Verify that if the value of a cookie is not meant to be accessible to client-side scripts (such as a session token), the cookie must have the 'HttpOnly' attribute set and the same value (e. g. session token) must only be transferred to the client via the 'Set-Cookie' header field. | E12: 2 | F12: Compliant | G12: Secure and HttpOnly cookies are explicitly required for authenticated staff sessions. | H12: DESOFS Phase 1: §5.1 RS1-RS3; AC5/AC8/AC11; STRIDE P5/P6; §12 tests
A13: V3.3 | B13: Cookie Setup | C13: V3.3.5 | D13: Verify that when the application writes a cookie, the cookie name and value length combined are not over 4096 bytes. Overly large cookies will not be stored by the browser and therefore not sent with requests, preventing the user from using application functionality which relies on that cookie. | E13: 3 | F13: Not Started | G13: Browser cookie behavior is partly covered through secure session requirements; exact header details pending. | H13: DESOFS Phase 1: §5.1 RS1-RS3; AC5/AC8/AC11; STRIDE P5/P6; §12 tests
A14: V3.4 | B14: Browser Security Mechanism Headers
A15: V3.4 | B15: Browser Security Mechanism Headers | C15: V3.4.1 | D15: Verify that a Strict-Transport-Security header field is included on all responses to enforce an HTTP Strict Transport Security (HSTS) policy. A maximum age of at least 1 year must be defined, and for L2 and up, the policy must apply to all subdomains as well. | E15: 1 | F15: Compliant | G15: HSTS is configured in Spring Security with includeSubDomains and max-age. | H15: SecurityConfig.java; SecurityHeadersTest
A16: V3.4 | B16: Browser Security Mechanism Headers | C16: V3.4.2 | D16: Verify that the Cross-Origin Resource Sharing (CORS) Access-Control-Allow-Origin header field is a fixed value by the application, or if the Origin HTTP request header field value is used, it is validated against an allowlist of trusted origins. When 'Access-Control-Allow-Origin: *' needs to be used, verify that the response does not include any sensitive information. | E16: 1 | F16: Not Started | G16: API is browser-consumable; origin allowlist/CORS policy should be documented in implementation. | H16: DESOFS Phase 1: DFD/trust boundaries §9; STRIDE §10; mitigations §13
A17: V3.4 | B17: Browser Security Mechanism Headers | C17: V3.4.3 | D17: Verify that HTTP responses include a Content-Security-Policy response header field which defines directives to ensure the browser only loads and executes trusted content or resources, in order to limit execution of malicious JavaScript. As a minimum, a global policy must be used which includes the directives object-src 'none' and base-uri 'none' and defines either an allowlist or uses nonces or hashes. For an L3 application, a per-response policy with nonces or hashes must be defined. | E17: 2 | F17: Not Started | G17: Not applicable in the current backend-only design; would be relevant if a browser-based client is introduced. | H17: DESOFS Phase 1: DFD/trust boundaries §9; STRIDE §10; mitigations §13
A18: V3.4 | B18: Browser Security Mechanism Headers | C18: V3.4.4 | D18: Verify that all HTTP responses contain an 'X-Content-Type-Options: nosniff' header field. This instructs browsers not to use content sniffing and MIME type guessing for the given response, and to require the response's Content-Type header field value to match the destination resource. For example, the response to a request for a style is only accepted if the response's Content-Type is 'text/css'. This also enables the use of the Cross-Origin Read Blocking (CORB) functionality by the browser. | E18: 2 | F18: Not Started | G18: Not applicable in the current backend-only design; would be relevant if a browser-based client is introduced. | H18: DESOFS Phase 1: DFD/trust boundaries §9; STRIDE §10; mitigations §13
A19: V3.4 | B19: Browser Security Mechanism Headers | C19: V3.4.5 | D19: Verify that the application sets a referrer policy to prevent leakage of technically sensitive data to third-party services via the 'Referer' HTTP request header field. This can be done using the Referrer-Policy HTTP response header field or via HTML element attributes. Sensitive data could include path and query data in the URL, and for internal non-public applications also the hostname. | E19: 2 | F19: Not Started | G19: Not applicable in the current backend-only design; would be relevant if a browser-based client is introduced. | H19: DESOFS Phase 1: DFD/trust boundaries §9; STRIDE §10; mitigations §13
A20: V3.4 | B20: Browser Security Mechanism Headers | C20: V3.4.6 | D20: Verify that the web application uses the frame-ancestors directive of the Content-Security-Policy header field for every HTTP response to ensure that it cannot be embedded by default and that embedding of specific resources is allowed only when necessary. Note that the X-Frame-Options header field, although supported by browsers, is obsolete and may not be relied upon. | E20: 2 | F20: Not Started | G20: Not applicable in the current backend-only design; would be relevant if a browser-based client is introduced. | H20: DESOFS Phase 1: DFD/trust boundaries §9; STRIDE §10; mitigations §13
A21: V3.4 | B21: Browser Security Mechanism Headers | C21: V3.4.7 | D21: Verify that the Content-Security-Policy header field specifies a location to report violations. | E21: 3 | F21: Not Started | G21: Not applicable in the current backend-only design; would be relevant if a browser-based client is introduced. | H21: DESOFS Phase 1: DFD/trust boundaries §9; STRIDE §10; mitigations §13
A22: V3.4 | B22: Browser Security Mechanism Headers | C22: V3.4.8 | D22: Verify that all HTTP responses that initiate a document rendering (such as responses with Content-Type text/html), include the Cross‑Origin‑Opener‑Policy header field with the same-origin directive or the same-origin-allow-popups directive as required. This prevents attacks that abuse shared access to Window objects, such as tabnabbing and frame counting. | E22: 3 | F22: Not Started | G22: Not applicable in the current backend-only design; would be relevant if a browser-based client is introduced. | H22: DESOFS Phase 1: DFD/trust boundaries §9; STRIDE §10; mitigations §13
A23: V3.5 | B23: Browser Origin Separation
A24: V3.5 | B24: Browser Origin Separation | C24: V3.5.1 | D24: Verify that, if the application does not rely on the CORS preflight mechanism to prevent disallowed cross-origin requests to use sensitive functionality, these requests are validated to ensure they originate from the application itself. This may be done by using and validating anti-forgery tokens or requiring extra HTTP header fields that are not CORS-safelisted request-header fields. This is to defend against browser-based request forgery attacks, commonly known as cross-site request forgery (CSRF). | E24: 1 | F24: Not Started | G24: No explicit CSRF or origin validation mechanism is defined in the backend design. | H24: DESOFS Phase 1: DFD/trust boundaries §9; STRIDE §10; mitigations §13
A25: V3.5 | B25: Browser Origin Separation | C25: V3.5.2 | D25: Verify that, if the application relies on the CORS preflight mechanism to prevent disallowed cross-origin use of sensitive functionality, it is not possible to call the functionality with a request which does not trigger a CORS-preflight request. This may require checking the values of the 'Origin' and 'Content-Type' request header fields or using an extra header field that is not a CORS-safelisted header-field. | E25: 1 | F25: Not Started | G25: CORS policy and origin validation are not explicitly defined in the design. | H25: DESOFS Phase 1: DFD/trust boundaries §9; STRIDE §10; mitigations §13
A26: V3.5 | B26: Browser Origin Separation | C26: V3.5.3 | D26: Verify that HTTP requests to sensitive functionality use appropriate HTTP methods such as POST, PUT, PATCH, or DELETE, and not methods defined by the HTTP specification as "safe" such as HEAD, OPTIONS, or GET. Alternatively, strict validation of the Sec-Fetch-* request header fields can be used to ensure that the request did not originate from an inappropriate cross-origin call, a navigation request, or a resource load (such as an image source) where this is not expected. | E26: 1 | F26: Compliant | G26: Sensitive operations use explicit Spring MVC HTTP method mappings and unsupported methods are handled consistently. | H26: Controller classes; GlobalExceptionHandler.java
A27: V3.5 | B27: Browser Origin Separation | C27: V3.5.4 | D27: Verify that separate applications are hosted on different hostnames to leverage the restrictions provided by same-origin policy, including how documents or scripts loaded by one origin can interact with resources from another origin and hostname-based restrictions on cookies. | E27: 2 | F27: Not Started | G27: Application deployment across different origins/hostnames is not defined in the design. | H27: DESOFS Phase 1: §5.1 RS1-RS3; AC5/AC8/AC11; STRIDE P5/P6; §12 tests
A28: V3.5 | B28: Browser Origin Separation | C28: V3.5.5 | D28: Verify that messages received by the postMessage interface are discarded if the origin of the message is not trusted, or if the syntax of the message is invalid. | E28: 2 | F28: Not Applicable | G28: Not applicable in the current backend-only design; this would only be relevant if a browser-based client were introduced. | H28: N/A – frontend/browser functionality not in current system scope
A29: V3.5 | B29: Browser Origin Separation | C29: V3.5.6 | D29: Verify that JSONP functionality is not enabled anywhere across the application to avoid Cross-Site Script Inclusion (XSSI) attacks. | E29: 3 | F29: Not Started | G29: No JSONP usage or related protections are defined in the backend design. | H29: DESOFS Phase 1: DFD/trust boundaries §9; STRIDE §10; mitigations §13
A30: V3.5 | B30: Browser Origin Separation | C30: V3.5.7 | D30: Verify that data requiring authorization is not included in script resource responses, like JavaScript files, to prevent Cross-Site Script Inclusion (XSSI) attacks. | E30: 3 | F30: Not Applicable | G30: Not applicable in the current backend-only design; this would only be relevant if a browser-based client were introduced. | H30: N/A – frontend/browser functionality not in current system scope
A31: V3.5 | B31: Browser Origin Separation | C31: V3.5.8 | D31: Verify that authenticated resources (such as images, videos, scripts, and other documents) can be loaded or embedded on behalf of the user only when intended. This can be accomplished by strict validation of the Sec-Fetch-* HTTP request header fields to ensure that the request did not originate from an inappropriate cross-origin call, or by setting a restrictive Cross-Origin-Resource-Policy HTTP response header field to instruct the browser to block returned content. | E31: 3 | F31: Not Started | G31: No controls for restricting cross-origin resource loading are defined in the design. | H31: DESOFS Phase 1: DFD/trust boundaries §9; STRIDE §10; mitigations §13
A32: V3.6 | B32: External Resource Integrity
A33: V3.6 | B33: External Resource Integrity | C33: V3.6.1 | D33: Verify that client-side assets, such as JavaScript libraries, CSS, or web fonts, are only hosted externally (e.g., on a Content Delivery Network) if the resource is static and versioned and Subresource Integrity (SRI) is used to validate the integrity of the asset. If this is not possible, there should be a documented security decision to justify this for each resource. | E33: 3 | F33: Not Applicable | G33: backend-only API; browser/UI feature not in scope | H33: Project.pdf: backend API, 3 roles, OS/file ops, ASVS deliverable
A34: V3.7 | B34: Other Browser Security Considerations
A35: V3.7 | B35: Other Browser Security Considerations | C35: V3.7.1 | D35: Verify that the application only uses client-side technologies which are still supported and considered secure. Examples of technologies which do not meet this requirement include NSAPI plugins, Flash, Shockwave, ActiveX, Silverlight, NACL, or client-side Java applets. | E35: 2 | F35: Not Applicable | G35: Not applicable in the current backend-only design; this would only be relevant if a browser-based client were introduced. | H35: N/A – frontend/browser functionality not in current system scope
A36: V3.7 | B36: Other Browser Security Considerations | C36: V3.7.2 | D36: Verify that the application will only automatically redirect the user to a different hostname or domain (which is not controlled by the application) where the destination appears on an allowlist. | E36: 2 | F36: Not Applicable | G36: Not applicable in the current backend-only design; this would only be relevant if a browser-based client were introduced. | H36: N/A – frontend/browser functionality not in current system scope
A37: V3.7 | B37: Other Browser Security Considerations | C37: V3.7.3 | D37: Verify that the application shows a notification when the user is being redirected to a URL outside of the application's control, with an option to cancel the navigation. | E37: 3 | F37: Not Started | G37: Backend project may later have a browser client; frontend/browser controls are mostly still to be specified. | H37: Project.pdf: backend API, 3 roles, OS/file ops, ASVS deliverable
A38: V3.7 | B38: Other Browser Security Considerations | C38: V3.7.4 | D38: Verify that the application's top-level domain (e.g., site.tld) is added to the public preload list for HTTP Strict Transport Security (HSTS). This ensures that the use of TLS for the application is built directly into the main browsers, rather than relying only on the Strict-Transport-Security response header field. | E38: 3 | F38: Not Started | G38: HTTPS is required, but HSTS preload configuration is not defined. | H38: DESOFS Phase 1: assumptions §2.2 HTTPS; §5.3 RS7; AC9/AC10
A39: V3.7 | B39: Other Browser Security Considerations | C39: V3.7.5 | D39: Verify that the application behaves as documented (such as warning the user or blocking access) if the browser used to access the application does not support the expected security features. | E39: 3 | F39: Not Started | G39: No browser-specific behavior or fallback mechanisms are defined in the design. | H39: Project.pdf: backend API, 3 roles, OS/file ops, ASVS deliverable

Sheet V4 - API and Web Service
A1: Section ID | B1: Section Name | C1: Req ID | D1: Description | E1: Level | F1: Status | G1: Observations | H1: Reference / Link
A2: V4.1 | B2: Generic Web Service Security
A3: V4.1 | B3: Generic Web Service Security | C3: V4.1.1 | D3: Verify that every HTTP response with a message body contains a Content-Type header field that matches the actual content of the response, including the charset parameter to specify safe character encoding (e.g., UTF-8, ISO-8859-1) according to IANA Media Types, such as "text/", "/+xml" and "/xml". | E3: 1 | F3: Compliant | G3: API responses are produced by Spring MVC and error responses are centralized as JSON through GlobalExceptionHandler. | H3: GlobalExceptionHandler.java; controller package
A4: V4.1 | B4: Generic Web Service Security | C4: V4.1.2 | D4: Verify that only user-facing endpoints (intended for manual web-browser access) automatically redirect from HTTP to HTTPS, while other services or endpoints do not implement transparent redirects. This is to avoid a situation where a client is erroneously sending unencrypted HTTP requests, but since the requests are being automatically redirected to HTTPS, the leakage of sensitive data goes undiscovered. | E4: 2 | F4: Not Started | G4: HTTPS is required, but redirect behavior between HTTP and HTTPS is not defined. | H4: DESOFS Phase 1: assumptions §2.2 HTTPS; §5.3 RS7; AC9/AC10
A5: V4.1 | B5: Generic Web Service Security | C5: V4.1.3 | D5: Verify that any HTTP header field used by the application and set by an intermediary layer, such as a load balancer, a web proxy, or a backend-for-frontend service, cannot be overridden by the end-user. Example headers might include X-Real-IP, X-Forwarded-*, or X-User-ID. | E5: 2 | F5: Not Started | G5: Proxy/load balancer header trust policy is not yet documented. | H5: DESOFS Phase 1: DFD/trust boundaries §9; STRIDE §10; mitigations §11
A6: V4.1 | B6: Generic Web Service Security | C6: V4.1.4 | D6: Verify that only HTTP methods that are explicitly supported by the application or its API (including OPTIONS during preflight requests) can be used and that unused methods are blocked. | E6: 3 | F6: Compliant | G6: Only explicitly mapped HTTP methods are supported by each controller endpoint; unsupported methods are rejected by Spring MVC. | H6: Controller classes; GlobalExceptionHandler.java
A7: V4.1 | B7: Generic Web Service Security | C7: V4.1.5 | D7: Verify that per-message digital signatures are used to provide additional assurance on top of transport protections for requests or transactions which are highly sensitive or which traverse a number of systems. | E7: 3 | F7: Not Applicable | G7: Not applicable in the current system design. | H7: N/A – not in current system scope
A8: V4.2 | B8: HTTP Message Structure Validation
A9: V4.2 | B9: HTTP Message Structure Validation | C9: V4.2.1 | D9: Verify that all application components (including load balancers, firewalls, and application servers) determine boundaries of incoming HTTP messages using the appropriate mechanism for the HTTP version to prevent HTTP request smuggling. In HTTP/1.x, if a Transfer-Encoding header field is present, the Content-Length header must be ignored per RFC 2616. When using HTTP/2 or HTTP/3, if a Content-Length header field is present, the receiver must ensure that it is consistent with the length of the DATA frames. | E9: 2 | F9: Not Started | G9: HTTP message parsing, header validation, and request handling controls are not explicitly defined in the system design. | H9: DESOFS Phase 1: DFD/trust boundaries §9; STRIDE §10; mitigations §11
A10: V4.2 | B10: HTTP Message Structure Validation | C10: V4.2.2 | D10: Verify that when generating HTTP messages, the Content-Length header field does not conflict with the length of the content as determined by the framing of the HTTP protocol, in order to prevent request smuggling attacks. | E10: 3 | F10: Not Started | G10: HTTP message parsing, header validation, and request handling controls are not explicitly defined in the system design. | H10: DESOFS Phase 1: DFD/trust boundaries §9; STRIDE §10; mitigations §11
A11: V4.2 | B11: HTTP Message Structure Validation | C11: V4.2.3 | D11: Verify that the application does not send nor accept HTTP/2 or HTTP/3 messages with connection-specific header fields such as Transfer-Encoding to prevent response splitting and header injection attacks. | E11: 3 | F11: Not Started | G11: HTTP message parsing, header validation, and request handling controls are not explicitly defined in the system design. | H11: DESOFS Phase 1: DFD/trust boundaries §9; STRIDE §10; mitigations §11
A12: V4.2 | B12: HTTP Message Structure Validation | C12: V4.2.4 | D12: Verify that the application only accepts HTTP/2 and HTTP/3 requests where the header fields and values do not contain any CR (\r), LF (\n), or CRLF (\r\n) sequences, to prevent header injection attacks. | E12: 3 | F12: Not Started | G12: HTTP message parsing, header validation, and request handling controls are not explicitly defined in the system design. | H12: DESOFS Phase 1: DFD/trust boundaries §9; STRIDE §10; mitigations §11
A13: V4.2 | B13: HTTP Message Structure Validation | C13: V4.2.5 | D13: Verify that, if the application (backend or frontend) builds and sends requests, it uses validation, sanitization, or other mechanisms to avoid creating URIs (such as for API calls) or HTTP request header fields (such as Authorization or Cookie), which are too long to be accepted by the receiving component. This could cause a denial of service, such as when sending an overly long request (e.g., a long cookie header field), which results in the server always responding with an error status. | E13: 3 | F13: Not Started | G13: Input validation and request size constraints are not explicitly defined in the design. | H13: DESOFS Phase 1: DFD/trust boundaries §9; STRIDE §10; mitigations §11
A14: V4.3 | B14: GraphQL
A15: V4.3 | B15: GraphQL | C15: V4.3.1 | D15: Verify that a query allowlist, depth limiting, amount limiting, or query cost analysis is used to prevent GraphQL or data layer expression Denial of Service (DoS) as a result of expensive, nested queries. | E15: 2 | F15: Not Applicable | G15: Not applicable – the application does not expose a GraphQL interface. | H15: N/A – GraphQL not in current system scope
A16: V4.3 | B16: GraphQL | C16: V4.3.2 | D16: Verify that GraphQL introspection queries are disabled in the production environment unless the GraphQL API is meant to be used by other parties. | E16: 2 | F16: Not Applicable | G16: Not applicable – the application does not expose a GraphQL interface. | H16: N/A – GraphQL not in current system scope
A17: V4.4 | B17: WebSocket
A18: V4.4 | B18: WebSocket | C18: V4.4.1 | D18: Verify that WebSocket over TLS (WSS) is used for all WebSocket connections. | E18: 1 | F18: Not Applicable | G18: Not applicable – the application does not use WebSocket communication. | H18: N/A – WebSocket not in current system scope
A19: V4.4 | B19: WebSocket | C19: V4.4.2 | D19: Verify that, during the initial HTTP WebSocket handshake, the Origin header field is checked against a list of origins allowed for the application. | E19: 2 | F19: Not Applicable | G19: Not applicable – the application does not use WebSocket communication. | H19: N/A – WebSocket not in current system scope
A20: V4.4 | B20: WebSocket | C20: V4.4.3 | D20: Verify that, if the application's standard session management cannot be used, dedicated tokens are being used for this, which comply with the relevant Session Management security requirements. | E20: 2 | F20: Not Started | G20: WebSocket session management and token handling are not defined in the design. | H20: DESOFS Phase 1: DFD/trust boundaries §9; STRIDE §10; mitigations §11
A21: V4.4 | B21: WebSocket | C21: V4.4.4 | D21: Verify that dedicated WebSocket session management tokens are initially obtained or validated through the previously authenticated HTTPS session when transitioning an existing HTTPS session to a WebSocket channel. | E21: 2 | F21: Not Applicable | G21: Not applicable – the application does not use WebSocket communication. | H21: N/A – WebSocket not in current system scope

Sheet V5 - File Handling
A1: Section ID | B1: Section Name | C1: Req ID | D1: Description | E1: Level | F1: Status | G1: Observations | H1: Reference / Link
A2: V5.1 | B2: File Handling Documentation
A3: V5.1 | B3: File Handling Documentation | C3: V5.1.1 | D3: Verify that the documentation defines the permitted file types, expected file extensions, and maximum size (including unpacked size) for each upload feature. Additionally, ensure that the documentation specifies how files are made safe for end-users to download and process, such as how the application behaves when a malicious file is detected. | E3: 2 | F3: In Progress | G3: Allowed file types, extensions and maximum file size are documented and implemented. Real malware scanning and full malicious-file workflow are not implemented yet. | H3: Sprint 1 report ?6; FileStorageService.java
A4: V5.2 | B4: File Upload and Content
A5: V5.2 | B5: File Upload and Content | C5: V5.2.1 | D5: Verify that the application will only accept files of a size which it can process without causing a loss of performance or a denial of service attack. | E5: 1 | F5: Compliant | G5: Each uploaded file is limited to 10 MB before processing. | H5: FileStorageService.java; FileStorageServiceTest
A6: V5.2 | B6: File Upload and Content | C6: V5.2.2 | D6: Verify that when the application accepts a file, either on its own or within an archive such as a zip file, it checks if the file extension matches an expected file extension and validates that the contents correspond to the type represented by the extension. This includes, but is not limited to, checking the initial 'magic bytes', performing image re-writing, and using specialized libraries for file content validation. For L1, this can focus just on files which are used to make specific business or security decisions. For L2 and up, this must apply to all files being accepted. | E6: 1 | F6: Compliant | G6: Uploads are validated by MIME type, extension and magic bytes/signature for supported file types. | H6: FileStorageService.java; ReportControllerAttachmentUploadTest; FileStorageServiceTest
A7: V5.2 | B7: File Upload and Content | C7: V5.2.3 | D7: Verify that the application checks compressed files (e.g., zip, gz, docx, odt) against maximum allowed uncompressed size and against maximum number of files before uncompressing the file. | E7: 2 | F7: Not Applicable | G7: Not applicable – the documented upload scope does not include compressed archive handling. | H7: N/A – archive upload handling not in current system scope
A8: V5.2 | B8: File Upload and Content | C8: V5.2.4 | D8: Verify that a file size quota and maximum number of files per user are enforced to ensure that a single user cannot fill up the storage with too many files, or excessively large files. | E8: 3 | F8: In Progress | G8: Per-file size limits and upload rate limiting exist, but global/user storage quotas and maximum file count quotas are not implemented. | H8: RateLimiterService.java; FileStorageService.java; Sprint 1 limitations
A9: V5.2 | B9: File Upload and Content | C9: V5.2.5 | D9: Verify that the application does not allow uploading compressed files containing symlinks unless this is specifically required (in which case it will be necessary to enforce an allowlist of the files that can be symlinked to). | E9: 3 | F9: Not Applicable | G9: Not applicable – the documented upload scope does not include compressed archive handling. | H9: N/A – archive upload handling not in current system scope
A10: V5.2 | B10: File Upload and Content | C10: V5.2.6 | D10: Verify that the application rejects uploaded images with a pixel size larger than the maximum allowed, to prevent pixel flood attacks. | E10: 3 | F10: Not Applicable | G10: Not applicable – the design does not include image-processing functionality requiring pixel flood controls. | H10: N/A – image processing not in current system scope
A11: V5.3 | B11: File Storage
A12: V5.3 | B12: File Storage | C12: V5.3.1 | D12: Verify that files uploaded or generated by untrusted input and stored in a public folder, are not executed as server-side program code when accessed directly with an HTTP request. | E12: 1 | F12: Compliant | G12: Uploaded files are stored in a controlled directory outside the static frontend resources and are not executed as server-side code. | H12: FileStorageService.java
A13: V5.3 | B13: File Storage | C13: V5.3.2 | D13: Verify that when the application creates file paths for file operations, instead of user-submitted filenames, it uses internally generated or trusted data, or if user-submitted filenames or file metadata must be used, strict validation and sanitization must be applied. This is to protect against path traversal, local or remote file inclusion (LFI, RFI), and server-side request forgery (SSRF) attacks. | E13: 1 | F13: Compliant | G13: Stored filenames are generated internally using UUID/file references instead of trusting user-submitted filenames. | H13: FileStorageService.java; SafeFilename.java
A14: V5.3 | B14: File Storage | C14: V5.3.3 | D14: Verify that server-side file processing, such as file decompression, ignores user-provided path information to prevent vulnerabilities such as zip slip. | E14: 3 | F14: Not Applicable | G14: Not applicable – server-side file decompression is not part of the current design. | H14: N/A – decompression not in current system scope
A15: V5.4 | B15: File Download
A16: V5.4 | B16: File Download | C16: V5.4.1 | D16: Verify that the application validates or ignores user-submitted filenames, including in a JSON, JSONP, or URL parameter and specifies a filename in the Content-Disposition header field in the response. | E16: 2 | F16: Compliant | G16: User-submitted filenames are validated/sanitized by SafeFilename and dangerous path separators/extensions are rejected. | H16: SafeFilename.java; SafeFilenameTest; SafeFilenameSecurityTest
A17: V5.4 | B17: File Download | C17: V5.4.2 | D17: Verify that file names served (e.g., in HTTP response header fields or email attachments) are encoded or sanitized (e.g., following RFC 6266) to preserve document structure and prevent injection attacks. | E17: 2 | F17: In Progress | G17: Stored names are safe and generated internally. Further Content-Disposition filename encoding hardening can be improved in future work. | H17: FileStorageService.java; ReportService.java
A18: V5.4 | B18: File Download | C18: V5.4.3 | D18: Verify that files obtained from untrusted sources are scanned by antivirus scanners to prevent serving of known malicious content. | E18: 2 | F18: Not Started | G18: Real antivirus or malware scanning is not implemented in Sprint 1. Current controls are validation/allowlisting only. | H18: Sprint 1 limitations

Sheet V6 - Authentication
A1: Section ID | B1: Section Name | C1: Req ID | D1: Description | E1: Level | F1: Status | G1: Observations | H1: Reference / Link
A2: V6.1 | B2: Authentication Documentation
A3: V6.1 | B3: Authentication Documentation | C3: V6.1.1 | D3: Verify that application documentation defines how controls such as rate limiting, anti-automation, and adaptive response, are used to defend against attacks such as credential stuffing and password brute force. The documentation must make clear how these controls are configured and prevent malicious account lockout. | E3: 1 | F3: In Progress | G3: Rate limiting is documented and implemented for public tracking/upload/download flows, but login-specific brute-force protection is not yet implemented. | H3: RateLimiterService.java; Sprint 1 report ?7
A4: V6.1 | B4: Authentication Documentation | C4: V6.1.2 | D4: Verify that a list of context-specific words is documented in order to prevent their use in passwords. The list could include permutations of organization names, product names, system identifiers, project codenames, department or role names, and similar. | E4: 2 | F4: Not Started | G4: No context-specific password denylist is defined in the design. | H4: DESOFS Phase 1: §6.1 RS2; §6.3 RS8
A5: V6.1 | B5: Authentication Documentation | C5: V6.1.3 | D5: Verify that, if the application includes multiple authentication pathways, these are all documented together with the security controls and authentication strength which must be consistently enforced across them. | E5: 2 | F5: Not Applicable | G5: Only one authenticated pathway for internal users is defined in the design. | H5: DESOFS Phase 1: §2.1 Stakeholders; §6.1 RS2
A6: V6.2 | B6: Password Security
A7: V6.2 | B7: Password Security | C7: V6.2.1 | D7: Verify that user set passwords are at least 8 characters in length although a minimum of 15 characters is strongly recommended. | E7: 1 | F7: Compliant | G7: Admin-created user passwords require 12 to 128 characters. | H7: CreateUserRequest.java
A8: V6.2 | B8: Password Security | C8: V6.2.2 | D8: Verify that users can change their password. | E8: 1 | F8: Not Started | G8: Internal user authentication is in scope, but the password policy is not explicitly defined in the design. | H8: DESOFS Phase 1: §6.1 RS2; §6.3 RS9
A9: V6.2 | B9: Password Security | C9: V6.2.3 | D9: Verify that password change functionality requires the user's current and new password. | E9: 1 | F9: Not Started | G9: Internal user authentication is in scope, but the password policy is not explicitly defined in the design. | H9: DESOFS Phase 1: §6.1 RS2; §6.3 RS10
A10: V6.2 | B10: Password Security | C10: V6.2.4 | D10: Verify that passwords submitted during account registration or password change are checked against an available set of, at least, the top 3000 passwords which match the application's password policy, e.g. minimum length. | E10: 1 | F10: Not Started | G10: Internal user authentication is in scope, but the password policy is not explicitly defined in the design. | H10: DESOFS Phase 1: §6.1 RS2; §6.3 RS11
A11: V6.2 | B11: Password Security | C11: V6.2.5 | D11: Verify that passwords of any composition can be used, without rules limiting the type of characters permitted. There must be no requirement for a minimum number of upper or lower case characters, numbers, or special characters. | E11: 1 | F11: In Progress | G11: Passwords may include special characters and are not modified before verification, but the current policy enforces composition rules, so further ASVS alignment is possible. | H11: CreateUserRequest.java
A12: V6.2 | B12: Password Security | C12: V6.2.6 | D12: Verify that password input fields use type=password to mask the entry. Applications may allow the user to temporarily view the entire masked password, or the last typed character of the password. | E12: 1 | F12: Not Applicable | G12: Not applicable in the current system design. | H12: N/A – not in current system scope
A13: V6.2 | B13: Password Security | C13: V6.2.7 | D13: Verify that "paste" functionality, browser password helpers, and external password managers are permitted. | E13: 1 | F13: Not Applicable | G13: Not applicable in the current system design. | H13: N/A – not in current system scope
A14: V6.2 | B14: Password Security | C14: V6.2.8 | D14: Verify that the application verifies the user's password exactly as received from the user, without any modifications such as truncation or case transformation. | E14: 1 | F14: Compliant | G14: Passwords are passed to Spring Security authentication/password encoding without trimming, case conversion or other normalization by the application. | H14: AuthService.java; UserService.java
A15: V6.2 | B15: Password Security | C15: V6.2.9 | D15: Verify that passwords of at least 64 characters are permitted. | E15: 2 | F15: Not Started | G15: Password handling requirements for internal users are in scope, but these controls are not explicitly defined in the design. | H15: DESOFS Phase 1: §6.1 RS2; §6.3 RS9
A16: V6.2 | B16: Password Security | C16: V6.2.10 | D16: Verify that a user's password stays valid until it is discovered to be compromised or the user rotates it. The application must not require periodic credential rotation. | E16: 2 | F16: Not Started | G16: Password handling requirements for internal users are in scope, but these controls are not explicitly defined in the design. | H16: DESOFS Phase 1: §6.1 RS2; §6.3 RS10
A17: V6.2 | B17: Password Security | C17: V6.2.11 | D17: Verify that the documented list of context specific words is used to prevent easy to guess passwords being created. | E17: 2 | F17: Not Started | G17: Password handling requirements for internal users are in scope, but these controls are not explicitly defined in the design. | H17: DESOFS Phase 1: §6.1 RS2; §6.3 RS11
A18: V6.2 | B18: Password Security | C18: V6.2.12 | D18: Verify that passwords submitted during account registration or password changes are checked against a set of breached passwords. | E18: 2 | F18: Not Started | G18: Password handling requirements for internal users are in scope, but these controls are not explicitly defined in the design. | H18: DESOFS Phase 1: §6.1 RS2; §6.3 RS12
A19: V6.3 | B19: General Authentication Security
A20: V6.3 | B20: General Authentication Security | C20: V6.3.1 | D20: Verify that controls to prevent attacks such as credential stuffing and password brute force are implemented according to the application's security documentation. | E20: 1 | F20: In Progress | G20: Credential brute-force controls are planned. Current Sprint 1 rate limiting focuses on public report flows, not login attempts. | H20: Sprint 1 report ?7; RateLimiterService.java
A21: V6.3 | B21: General Authentication Security | C21: V6.3.2 | D21: Verify that default user accounts (e.g., "root", "admin", or "sa") are not present in the application or are disabled. | E21: 1 | F21: Compliant | G21: Seed users are restricted to dev/test profiles and controlled by configuration, avoiding automatic production default accounts. | H21: DataInitializer.java; DataInitializerDisabledTest
A22: V6.3 | B22: General Authentication Security | C22: V6.3.3 | D22: Verify that either a multi-factor authentication mechanism or a combination of single-factor authentication mechanisms, must be used in order to access the application. For L3, one of the factors must be a hardware-based authentication mechanism which provides compromise and impersonation resistance against phishing attacks while verifying the intent to authenticate by requiring a user-initiated action (such as a button press on a FIDO hardware key or a mobile phone). Relaxing any of the considerations in this requirement requires a fully documented rationale and a comprehensive set of mitigating controls. | E22: 2 | F22: Not Started | G22: MFA is not implemented in Sprint 1 and remains future work for privileged roles. | H22: Sprint 1 limitations
A23: V6.3 | B23: General Authentication Security | C23: V6.3.4 | D23: Verify that, if the application includes multiple authentication pathways, there are no undocumented pathways and that security controls and authentication strength are enforced consistently. | E23: 2 | F23: Not Applicable | G23: Only one authenticated pathway for staff users is defined in the design. | H23: DESOFS Phase 1: §6.1 RS2
A24: V6.3 | B24: General Authentication Security | C24: V6.3.5 | D24: Verify that users are notified of suspicious authentication attempts (successful or unsuccessful). This may include authentication attempts from an unusual location or client, partially successful authentication (only one of multiple factors), an authentication attempt after a long period of inactivity or a successful authentication after several unsuccessful attempts. | E24: 3 | F24: Not Started | G24: Advanced authentication notification/anti-enumeration controls are relevant but not yet specified. | H24: DESOFS Phase 1: §5.1 RS1-RS3; AC5/AC8/AC11; STRIDE P5/P6; §12 tests
A25: V6.3 | B25: General Authentication Security | C25: V6.3.6 | D25: Verify that email is not used as either a single-factor or multi-factor authentication mechanism. | E25: 3 | F25: Not Applicable | G25: Email-based authentication is not part of the authentication design. | H25: DESOFS Phase 1: §6.1 RS2-RS3
A26: V6.3 | B26: General Authentication Security | C26: V6.3.7 | D26: Verify that users are notified after updates to authentication details, such as credential resets or modification of the username or email address. | E26: 3 | F26: Not Started | G26: Advanced authentication notification/anti-enumeration controls are relevant but not yet specified. | H26: DESOFS Phase 1: §5.1 RS1-RS3; AC5/AC8/AC11; STRIDE P5/P6; §12 tests
A27: V6.3 | B27: General Authentication Security | C27: V6.3.8 | D27: Verify that valid users cannot be deduced from failed authentication challenges, such as by basing on error messages, HTTP response codes, or different response times. Registration and forgot password functionality must also have this protection. | E27: 3 | F27: Not Started | G27: Advanced authentication notification/anti-enumeration controls are relevant but not yet specified. | H27: DESOFS Phase 1: §5.1 RS1-RS3; AC5/AC8/AC11; STRIDE P5/P6; §12 tests
A28: V6.4 | B28: Authentication Factor Lifecycle and Recovery
A29: V6.4 | B29: Authentication Factor Lifecycle and Recovery | C29: V6.4.1 | D29: Verify that system generated initial passwords or activation codes are securely randomly generated, follow the existing password policy, and expire after a short period of time or after they are initially used. These initial secrets must not be permitted to become the long term password. | E29: 1 | F29: Not Applicable | G29: The application does not generate initial passwords or activation codes for users; admin supplies passwords subject to validation. | H29: AdminController.java; CreateUserRequest.java
A30: V6.4 | B30: Authentication Factor Lifecycle and Recovery | C30: V6.4.2 | D30: Verify that password hints or knowledge-based authentication (so-called "secret questions") are not present. | E30: 1 | F30: Not Applicable | G30: Password hints and security questions are not part of the authentication design. | H30: DESOFS Phase 1: §6.1 RS2-RS3
A31: V6.4 | B31: Authentication Factor Lifecycle and Recovery | C31: V6.4.3 | D31: Verify that a secure process for resetting a forgotten password is implemented, that does not bypass any enabled multi-factor authentication mechanisms. | E31: 2 | F31: Not Started | G31: Recovery/reset processes for internal users are possible but not yet specified in detail. | H31: DESOFS Phase 1: §5.1 RS1-RS3; AC5/AC8/AC11; STRIDE P5/P6; §12 tests
A32: V6.4 | B32: Authentication Factor Lifecycle and Recovery | C32: V6.4.4 | D32: Verify that if a multi-factor authentication factor is lost, evidence of identity proofing is performed at the same level as during enrollment. | E32: 2 | F32: Not Applicable | G32: MFA recovery is not applicable because MFA is not defined in the current design. | H32: DESOFS Phase 1: §6.1 RS2-RS3
A33: V6.4 | B33: Authentication Factor Lifecycle and Recovery | C33: V6.4.5 | D33: Verify that renewal instructions for authentication mechanisms which expire are sent with enough time to be carried out before the old authentication mechanism expires, configuring automated reminders if necessary. | E33: 3 | F33: Not Started | G33: MFA recovery is not applicable because MFA is not defined in the current design. | H33: DESOFS Phase 1: §5.1 RS1-RS3; AC5/AC8/AC11; STRIDE P5/P6; §12 tests
A34: V6.4 | B34: Authentication Factor Lifecycle and Recovery | C34: V6.4.6 | D34: Verify that administrative users can initiate the password reset process for the user, but that this does not allow them to change or choose the user's password. This prevents a situation where they know the user's password. | E34: 3 | F34: Not Started | G34: Recovery/reset processes for internal users are possible but not yet specified in detail. | H34: DESOFS Phase 1: §5.1 RS1-RS3; AC5/AC8/AC11; STRIDE P5/P6; §12 tests
A35: V6.5 | B35: General Multi-factor authentication requirements
A36: V6.5 | B36: General Multi-factor authentication requirements | C36: V6.5.1 | D36: Verify that lookup secrets, out-of-band authentication requests or codes, and time-based one-time passwords (TOTPs) are only successfully usable once. | E36: 2 | F36: Not Applicable | G36: Not applicable – the current authentication design does not include MFA, out-of-band methods, cryptographic assertions, or external identity providers. | H36: N/A – not in current authentication scope
A37: V6.5 | B37: General Multi-factor authentication requirements | C37: V6.5.2 | D37: Verify that, when being stored in the application's backend, lookup secrets with less than 112 bits of entropy (19 random alphanumeric characters or 34 random digits) are hashed with an approved password storage hashing algorithm that incorporates a 32-bit random salt. A standard hash function can be used if the secret has 112 bits of entropy or more. | E37: 2 | F37: Not Applicable | G37: Not applicable – the current authentication design does not include MFA, out-of-band methods, cryptographic assertions, or external identity providers. | H37: N/A – not in current authentication scope
A38: V6.5 | B38: General Multi-factor authentication requirements | C38: V6.5.3 | D38: Verify that lookup secrets, out-of-band authentication code, and time-based one-time password seeds, are generated using a Cryptographically Secure Pseudorandom Number Generator (CSPRNG) to avoid predictable values. | E38: 2 | F38: Not Applicable | G38: Not applicable – the current authentication design does not include MFA, out-of-band methods, cryptographic assertions, or external identity providers. | H38: N/A – not in current authentication scope
A39: V6.5 | B39: General Multi-factor authentication requirements | C39: V6.5.4 | D39: Verify that lookup secrets and out-of-band authentication codes have a minimum of 20 bits of entropy (typically 4 random alphanumeric characters or 6 random digits is sufficient). | E39: 2 | F39: Not Applicable | G39: Not applicable – the current authentication design does not include MFA, out-of-band methods, cryptographic assertions, or external identity providers. | H39: N/A – not in current authentication scope
A40: V6.5 | B40: General Multi-factor authentication requirements | C40: V6.5.5 | D40: Verify that out-of-band authentication requests, codes, or tokens, as well as time-based one-time passwords (TOTPs) have a defined lifetime. Out of band requests must have a maximum lifetime of 10 minutes and for TOTP a maximum lifetime of 30 seconds. | E40: 2 | F40: Not Applicable | G40: Not applicable – the current authentication design does not include MFA, out-of-band methods, cryptographic assertions, or external identity providers. | H40: N/A – not in current authentication scope
A41: V6.5 | B41: General Multi-factor authentication requirements | C41: V6.5.6 | D41: Verify that any authentication factor (including physical devices) can be revoked in case of theft or other loss. | E41: 3 | F41: Not Applicable | G41: Not applicable – the current authentication design does not include MFA, out-of-band methods, cryptographic assertions, or external identity providers. | H41: N/A – not in current authentication scope
A42: V6.5 | B42: General Multi-factor authentication requirements | C42: V6.5.7 | D42: Verify that biometric authentication mechanisms are only used as secondary factors together with either something you have or something you know. | E42: 3 | F42: Not Applicable | G42: Not applicable – the current authentication design does not include MFA, out-of-band methods, cryptographic assertions, or external identity providers. | H42: N/A – not in current authentication scope
A43: V6.5 | B43: General Multi-factor authentication requirements | C43: V6.5.8 | D43: Verify that time-based one-time passwords (TOTPs) are checked based on a time source from a trusted service and not from an untrusted or client provided time. | E43: 3 | F43: Not Applicable | G43: Not applicable – the current authentication design does not include MFA, out-of-band methods, cryptographic assertions, or external identity providers. | H43: N/A – not in current authentication scope
A44: V6.6 | B44: Out-of-Band authentication mechanisms
A45: V6.6 | B45: Out-of-Band authentication mechanisms | C45: V6.6.1 | D45: Verify that authentication mechanisms using the Public Switched Telephone Network (PSTN) to deliver One-time Passwords (OTPs) via phone or SMS are offered only when the phone number has previously been validated, alternate stronger methods (such as Time based One-time Passwords) are also offered, and the service provides information on their security risks to users. For L3 applications, phone and SMS must not be available as options. | E45: 2 | F45: Not Applicable | G45: Not applicable – the current authentication design does not include MFA, out-of-band methods, cryptographic assertions, or external identity providers. | H45: N/A – not in current authentication scope
A46: V6.6 | B46: Out-of-Band authentication mechanisms | C46: V6.6.2 | D46: Verify that out-of-band authentication requests, codes, or tokens are bound to the original authentication request for which they were generated and are not usable for a previous or subsequent one. | E46: 2 | F46: Not Applicable | G46: Not applicable – the current authentication design does not include MFA, out-of-band methods, cryptographic assertions, or external identity providers. | H46: N/A – not in current authentication scope
A47: V6.6 | B47: Out-of-Band authentication mechanisms | C47: V6.6.3 | D47: Verify that a code based out-of-band authentication mechanism is protected against brute force attacks by using rate limiting. Consider also using a code with at least 64 bits of entropy. | E47: 2 | F47: Not Applicable | G47: Not applicable – the current authentication design does not include MFA, out-of-band methods, cryptographic assertions, or external identity providers. | H47: N/A – not in current authentication scope
A48: V6.6 | B48: Out-of-Band authentication mechanisms | C48: V6.6.4 | D48: Verify that, where push notifications are used for multi-factor authentication, rate limiting is used to prevent push bombing attacks. Number matching may also mitigate this risk. | E48: 3 | F48: Not Applicable | G48: Not applicable – the current authentication design does not include MFA, out-of-band methods, cryptographic assertions, or external identity providers. | H48: N/A – not in current authentication scope
A49: V6.7 | B49: Cryptographic authentication mechanism
A50: V6.7 | B50: Cryptographic authentication mechanism | C50: V6.7.1 | D50: Verify that the certificates used to verify cryptographic authentication assertions are stored in a way protects them from modification. | E50: 3 | F50: Not Applicable | G50: Not applicable – the current authentication design does not include MFA, out-of-band methods, cryptographic assertions, or external identity providers. | H50: N/A – not in current authentication scope
A51: V6.7 | B51: Cryptographic authentication mechanism | C51: V6.7.2 | D51: Verify that the challenge nonce is at least 64 bits in length, and statistically unique or unique over the lifetime of the cryptographic device. | E51: 3 | F51: Not Applicable | G51: Not applicable – the current authentication design does not include MFA, out-of-band methods, cryptographic assertions, or external identity providers. | H51: N/A – not in current authentication scope
A52: V6.8 | B52: Authentication with an Identity Provider
A53: V6.8 | B53: Authentication with an Identity Provider | C53: V6.8.1 | D53: Verify that, if the application supports multiple identity providers (IdPs), the user's identity cannot be spoofed via another supported identity provider (eg. by using the same user identifier). The standard mitigation would be for the application to register and identify the user using a combination of the IdP ID (serving as a namespace) and the user's ID in the IdP. | E53: 2 | F53: Not Applicable | G53: Not applicable – the current authentication design does not include MFA, out-of-band methods, cryptographic assertions, or external identity providers. | H53: N/A – not in current authentication scope
A54: V6.8 | B54: Authentication with an Identity Provider | C54: V6.8.2 | D54: Verify that the presence and integrity of digital signatures on authentication assertions (for example on JWTs or SAML assertions) are always validated, rejecting any assertions that are unsigned or have invalid signatures. | E54: 2 | F54: Not Applicable | G54: Not applicable – the current authentication design does not include MFA, out-of-band methods, cryptographic assertions, or external identity providers. | H54: N/A – not in current authentication scope
A55: V6.8 | B55: Authentication with an Identity Provider | C55: V6.8.3 | D55: Verify that SAML assertions are uniquely processed and used only once within the validity period to prevent replay attacks. | E55: 2 | F55: Not Applicable | G55: Not applicable – the current authentication design does not include MFA, out-of-band methods, cryptographic assertions, or external identity providers. | H55: N/A – not in current authentication scope
A56: V6.8 | B56: Authentication with an Identity Provider | C56: V6.8.4 | D56: Verify that, if an application uses a separate Identity Provider (IdP) and expects specific authentication strength, methods, or recentness for specific functions, the application verifies this using the information returned by the IdP. For example, if OIDC is used, this might be achieved by validating ID Token claims such as 'acr', 'amr', and 'auth_time' (if present). If the IdP does not provide this information, the application must have a documented fallback approach that assumes that the minimum strength authentication mechanism was used (for example, single-factor authentication using username and password). | E56: 2 | F56: Not Applicable | G56: Not applicable – the current authentication design does not include MFA, out-of-band methods, cryptographic assertions, or external identity providers. | H56: N/A – not in current authentication scope

Sheet V7 - Session Management
A1: Section ID | B1: Section Name | C1: Req ID | D1: Description | E1: Level | F1: Status | G1: Observations | H1: Reference / Link
A2: V7.1 | B2: Session Management Documentation
A3: V7.1 | B3: Session Management Documentation | C3: V7.1.1 | D3: Verify that the user's session inactivity timeout and absolute maximum session lifetime are documented, are appropriate in combination with other controls, and that the documentation includes justification for any deviations from NIST SP 800-63B re-authentication requirements. | E3: 2 | F3: Compliant | G3: JWT lifetime is documented and configurable; default expiration is 3600 seconds. | H3: JwtService.java; application.yaml; Sprint 1 report ?3
A4: V7.1 | B4: Session Management Documentation | C4: V7.1.2 | D4: Verify that the documentation defines how many concurrent (parallel) sessions are allowed for one account as well as the intended behaviors and actions to be taken when the maximum number of active sessions is reached. | E4: 2 | F4: Not Started | G4: Concurrent-session policy for staff users is not yet documented. | H4: DESOFS Phase 1: §5.1 RS1-RS3; AC5/AC8/AC11; STRIDE P5/P6; §12 tests
A5: V7.1 | B5: Session Management Documentation | C5: V7.1.3 | D5: Verify that all systems that create and manage user sessions as part of a federated identity management ecosystem (such as SSO systems) are documented along with controls to coordinate session lifetimes, termination, and any other conditions that require re-authentication. | E5: 2 | F5: Not Applicable | G5: Not applicable – the current session design does not use federated identity or SSO. | H5: N/A – federated identity not in current system scope
A6: V7.2 | B6: Fundamental Session Management Security
A7: V7.2 | B7: Fundamental Session Management Security | C7: V7.2.1 | D7: Verify that the application performs all session token verification using a trusted, backend service. | E7: 1 | F7: Compliant | G7: JWT validation is performed by trusted backend components JwtAuthenticationFilter and JwtService. | H7: JwtAuthenticationFilter.java; JwtService.java
A8: V7.2 | B8: Fundamental Session Management Security | C8: V7.2.2 | D8: Verify that the application uses either self-contained or reference tokens that are dynamically generated for session management, i.e. not using static API secrets and keys. | E8: 1 | F8: Compliant | G8: Session state is represented by dynamically generated JWT Bearer tokens, not static API secrets. | H8: JwtService.java; AuthService.java
A9: V7.2 | B9: Fundamental Session Management Security | C9: V7.2.3 | D9: Verify that if reference tokens are used to represent user sessions, they are unique and generated using a cryptographically secure pseudo-random number generator (CSPRNG) and possess at least 128 bits of entropy. | E9: 1 | F9: Not Applicable | G9: The application uses self-contained JWTs, not reference tokens. | H9: JwtService.java
A10: V7.2 | B10: Fundamental Session Management Security | C10: V7.2.4 | D10: Verify that the application generates a new session token on user authentication, including re-authentication, and terminates the current session token. | E10: 1 | F10: Compliant | G10: A new JWT is generated on each successful authentication. | H10: AuthService.java; JwtService.java
A11: V7.3 | B11: Session Timeout
A12: V7.3 | B12: Session Timeout | C12: V7.3.1 | D12: Verify that there is an inactivity timeout such that re-authentication is enforced according to risk analysis and documented security decisions. | E12: 2 | F12: In Progress | G12: JWT absolute lifetime is implemented, but inactivity timeout/sliding session behavior is not implemented for stateless tokens. | H12: JwtService.java; Sprint 1 limitations
A13: V7.3 | B13: Session Timeout | C13: V7.3.2 | D13: Verify that there is an absolute maximum session lifetime such that re-authentication is enforced according to risk analysis and documented security decisions. | E13: 2 | F13: Compliant | G13: JWT expiration enforces an absolute maximum lifetime. | H13: JwtService.java
A14: V7.4 | B14: Session Termination
A15: V7.4 | B15: Session Termination | C15: V7.4.1 | D15: Verify that when session termination is triggered (such as logout or expiration), the application disallows any further use of the session. For reference tokens or stateful sessions, this means invalidating the session data at the application backend. Applications using self-contained tokens will need a solution such as maintaining a list of terminated tokens, disallowing tokens produced before a per-user date and time or rotating a per-user signing key. | E15: 1 | F15: In Progress | G15: Expired JWTs are rejected, but explicit server-side logout/revocation is not implemented for stateless tokens. | H15: JwtService.java; JwtAuthenticationFilter.java
A16: V7.4 | B16: Session Termination | C16: V7.4.2 | D16: Verify that the application terminates all active sessions when a user account is disabled or deleted (such as an employee leaving the company). | E16: 1 | F16: Not Started | G16: Disabling/deleting a staff account should terminate sessions, but this behavior is not yet documented. | H16: DESOFS Phase 1: §5.1 RS1-RS3; AC5/AC8/AC11; STRIDE P5/P6; §12 tests
A17: V7.4 | B17: Session Termination | C17: V7.4.3 | D17: Verify that the application gives the option to terminate all other active sessions after a successful change or removal of any authentication factor (including password change via reset or recovery and, if present, an MFA settings update). | E17: 2 | F17: Not Started | G17: Terminate-other-session behavior after auth-factor changes is not yet specified. | H17: DESOFS Phase 1: §5.1 RS1-RS3; AC5/AC8/AC11; STRIDE P5/P6; §12 tests
A18: V7.4 | B18: Session Termination | C18: V7.4.4 | D18: Verify that all pages that require authentication have easy and visible access to logout functionality. | E18: 2 | F18: Not Applicable | G18: Not applicable in the current system design. | H18: N/A – not in current system scope
A19: V7.4 | B19: Session Termination | C19: V7.4.5 | D19: Verify that application administrators are able to terminate active sessions for an individual user or for all users. | E19: 2 | F19: Not Started | G19: Admin session revocation capability would fit the design, but is not yet specified. | H19: DESOFS Phase 1: §5.1 RS1-RS3; AC5/AC8/AC11; STRIDE P5/P6; §12 tests
A20: V7.5 | B20: Defenses Against Session Abuse
A21: V7.5 | B21: Defenses Against Session Abuse | C21: V7.5.1 | D21: Verify that the application requires full re-authentication before allowing modifications to sensitive account attributes which may affect authentication such as email address, phone number, MFA configuration, or other information used in account recovery. | E21: 2 | F21: Not Started | G21: Sensitive-account-operation re-authentication/session management is not yet fully defined. | H21: DESOFS Phase 1: §5.1 RS1-RS3; AC5/AC8/AC11; STRIDE P5/P6; §12 tests
A22: V7.5 | B22: Defenses Against Session Abuse | C22: V7.5.2 | D22: Verify that users are able to view and (having authenticated again with at least one factor) terminate any or all currently active sessions. | E22: 2 | F22: Not Started | G22: Sensitive-account-operation re-authentication/session management is not yet fully defined. | H22: DESOFS Phase 1: §5.1 RS1-RS3; AC5/AC8/AC11; STRIDE P5/P6; §12 tests
A23: V7.5 | B23: Defenses Against Session Abuse | C23: V7.5.3 | D23: Verify that the application requires further authentication with at least one factor or secondary verification before performing highly sensitive transactions or operations. | E23: 3 | F23: Not Started | G23: Sensitive-account-operation re-authentication/session management is not yet fully defined. | H23: DESOFS Phase 1: §5.1 RS1-RS3; AC5/AC8/AC11; STRIDE P5/P6; §12 tests
A24: V7.6 | B24: Federated Re-authentication
A25: V7.6 | B25: Federated Re-authentication | C25: V7.6.1 | D25: Verify that session lifetime and termination between Relying Parties (RPs) and Identity Providers (IdPs) behave as documented, requiring re-authentication as necessary such as when the maximum time between IdP authentication events is reached. | E25: 2 | F25: Not Applicable | G25: Not applicable – the current session design does not use federated identity or SSO. | H25: N/A – federated identity not in current system scope
A26: V7.6 | B26: Federated Re-authentication | C26: V7.6.2 | D26: Verify that creation of a session requires either the user's consent or an explicit action, preventing the creation of new application sessions without user interaction. | E26: 2 | F26: Not Applicable | G26: Not applicable – the current session design does not use federated identity or SSO. | H26: N/A – federated identity not in current system scope

Sheet V8 - Authorization
A1: Section ID | B1: Section Name | C1: Req ID | D1: Description | E1: Level | F1: Status | G1: Observations | H1: Reference / Link
A2: V8.1 | B2: Authorization Documentation
A3: V8.1 | B3: Authorization Documentation | C3: V8.1.1 | D3: Verify that authorization documentation defines rules for restricting function-level and data-specific access based on consumer permissions and resource attributes. | E3: 1 | F3: Compliant | G3: RBAC roles and endpoint permissions are documented and implemented centrally in SecurityConfig. | H3: SecurityConfig.java; Sprint 1 report ?4
A4: V8.1 | B4: Authorization Documentation | C4: V8.1.2 | D4: Verify that authorization documentation defines rules for field-level access restrictions (both read and write) based on consumer permissions and resource attributes. Note that these rules might depend on other attribute values of the relevant data object, such as state or status. | E4: 2 | F4: In Progress | G4: Role and ownership rules are documented. Full field-level read/write authorization matrix is not yet exhaustive. | H4: Sprint 1 report ?4
A5: V8.1 | B5: Authorization Documentation | C5: V8.1.3 | D5: Verify that the application's documentation defines the environmental and contextual attributes (including but not limited to, time of day, user location, IP address, or device) that are used in the application to make security decisions, including those pertaining to authentication and authorization. | E5: 3 | F5: Not Applicable | G5: Not applicable – the authorization design does not use environmental or contextual attributes such as location, device, or time of day. | H5: N/A – contextual/adaptive authorization not in current scope
A6: V8.1 | B6: Authorization Documentation | C6: V8.1.4 | D6: Verify that authentication and authorization documentation defines how environmental and contextual factors are used in decision-making, in addition to function-level, data-specific, and field-level authorization. This should include the attributes evaluated, thresholds for risk, and actions taken (e.g., allow, challenge, deny, step-up authentication). | E6: 3 | F6: Not Applicable | G6: Not applicable – the authorization design does not use environmental or contextual attributes such as location, device, or time of day. | H6: N/A – contextual/adaptive authorization not in current scope
A7: V8.2 | B7: General Authorization Design
A8: V8.2 | B8: General Authorization Design | C8: V8.2.1 | D8: Verify that the application ensures that function-level access is restricted to consumers with explicit permissions. | E8: 1 | F8: Compliant | G8: Function-level access is enforced with Spring Security matchers for admin, analyst and audit endpoints. | H8: SecurityConfig.java; AdminAuthorizationTest; AuditorAuthorizationTest
A9: V8.2 | B9: General Authorization Design | C9: V8.2.2 | D9: Verify that the application ensures that data-specific access is restricted to consumers with explicit permissions to specific data items to mitigate insecure direct object reference (IDOR) and broken object level authorization (BOLA). | E9: 1 | F9: Compliant | G9: Data-specific authorization is enforced for analyst ownership and case/package operations. | H9: ReportService.java; CasePackageService.java; AnalystCaseOwnershipTest
A10: V8.2 | B10: General Authorization Design | C10: V8.2.3 | D10: Verify that the application ensures that field-level access is restricted to consumers with explicit permissions to specific fields to mitigate broken object property level authorization (BOPLA). | E10: 2 | F10: Not Started | G10: Property/field-level access control is not yet detailed in the documentation. | H10: DESOFS Phase 1: §5.1 RS1-RS3; AC5/AC8/AC11; STRIDE P5/P6; §12 tests
A11: V8.2 | B11: General Authorization Design | C11: V8.2.4 | D11: Verify that adaptive security controls based on a consumer's environmental and contextual attributes (such as time of day, location, IP address, or device) are implemented for authentication and authorization decisions, as defined in the application's documentation. These controls must be applied when the consumer tries to start a new session and also during an existing session. | E11: 3 | F11: Not Applicable | G11: Not applicable – the authorization design does not use environmental or contextual attributes such as location, device, or time of day. | H11: N/A – contextual/adaptive authorization not in current scope
A12: V8.3 | B12: Operation Level Authorization
A13: V8.3 | B13: Operation Level Authorization | C13: V8.3.1 | D13: Verify that the application enforces authorization rules at a trusted service layer and doesn't rely on controls that an untrusted consumer could manipulate, such as client-side JavaScript. | E13: 1 | F13: Compliant | G13: Authorization is enforced in backend security/service layers rather than client-side controls. | H13: SecurityConfig.java; service layer
A14: V8.3 | B14: Operation Level Authorization | C14: V8.3.2 | D14: Verify that changes to values on which authorization decisions are made are applied immediately. Where changes cannot be applied immediately, (such as when relying on data in self-contained tokens), there must be mitigating controls to alert when a consumer performs an action when they are no longer authorized to do so and revert the change. Note that this alternative would not mitigate information leakage. | E14: 3 | F14: Not Started | G14: Immediate propagation of permission changes is not explicitly defined in the design. | H14: System design (not explicitly defined)
A15: V8.3 | B15: Operation Level Authorization | C15: V8.3.3 | D15: Verify that access to an object is based on the originating subject's (e.g. consumer's) permissions, not on the permissions of any intermediary or service acting on their behalf. For example, if a consumer calls a web service using a self-contained token for authentication, and the service then requests data from a different service, the second service will use the consumer's token, rather than a machine-to-machine token from the first service, to make permission decisions. | E15: 3 | F15: Not Applicable | G15: Not applicable in the current system design. | H15: N/A – not in current system scope
A16: V8.4 | B16: Other Authorization Considerations
A17: V8.4 | B17: Other Authorization Considerations | C17: V8.4.1 | D17: Verify that multi-tenant applications use cross-tenant controls to ensure consumer operations will never affect tenants with which they do not have permissions to interact. | E17: 2 | F17: Not Applicable | G17: Not applicable – the application is not designed as a multi-tenant system. | H17: N/A – multi-tenant controls not in current system scope
A18: V8.4 | B18: Other Authorization Considerations | C18: V8.4.2 | D18: Verify that access to administrative interfaces incorporates multiple layers of security, including continuous consumer identity verification, device security posture assessment, and contextual risk analysis, ensuring that network location or trusted endpoints are not the sole factors for authorization even though they may reduce the likelihood of unauthorized access. | E18: 3 | F18: Not Started | G18: Administrative access is protected by RBAC, but advanced layered controls such as MFA, device posture, and contextual risk analysis are not defined. | H18: DESOFS Phase 1: §5.1 RS1-RS3; §8 STRIDE; §12 tests

Sheet V9 - Self-contained Tokens
A1: Section ID | B1: Section Name | C1: Req ID | D1: Description | E1: Level | F1: Status | G1: Observations | H1: Reference / Link
A2: V9.1 | B2: Token source and integrity
A3: V9.1 | B3: Token source and integrity | C3: V9.1.1 | D3: Verify that self-contained tokens are validated using their digital signature or MAC to protect against tampering before accepting the token's contents. | E3: 1 | F3: Compliant | G3: JWTs are validated using HMAC-SHA256 before claims are trusted. | H3: JwtService.java; JwtAuthenticationFilter.java
A4: V9.1 | B4: Token source and integrity | C4: V9.1.2 | D4: Verify that only algorithms on an allowlist can be used to create and verify self-contained tokens, for a given context. The allowlist must include the permitted algorithms, ideally only either symmetric or asymmetric algorithms, and must not include the 'None' algorithm. If both symmetric and asymmetric must be supported, additional controls will be needed to prevent key confusion. | E4: 1 | F4: Compliant | G4: The implementation uses a fixed HS256/HMAC-SHA256 flow and does not accept the none algorithm from token headers. | H4: JwtService.java
A5: V9.1 | B5: Token source and integrity | C5: V9.1.3 | D5: Verify that key material that is used to validate self-contained tokens is from trusted pre-configured sources for the token issuer, preventing attackers from specifying untrusted sources and keys. For JWTs and other JWS structures, headers such as 'jku', 'x5u', and 'jwk' must be validated against an allowlist of trusted sources. | E5: 1 | F5: Compliant | G5: JWT signing key material is loaded from configured application properties/environment and not from untrusted token header locations. | H5: JwtService.java; application.yaml
A6: V9.2 | B6: Token content
A7: V9.2 | B7: Token content | C7: V9.2.1 | D7: Verify that, if a validity time span is present in the token data, the token and its content are accepted only if the verification time is within this validity time span. For example, for JWTs, the claims 'nbf' and 'exp' must be verified. | E7: 1 | F7: Compliant | G7: JWT exp claim is generated and checked during validation. | H7: JwtService.java
A8: V9.2 | B8: Token content | C8: V9.2.2 | D8: Verify that the service receiving a token validates the token to be the correct type and is meant for the intended purpose before accepting the token's contents. For example, only access tokens can be accepted for authorization decisions and only ID Tokens can be used for proving user authentication. | E8: 2 | F8: In Progress | G8: Tokens are used as access tokens for backend authorization. Explicit token type/audience claims are not yet implemented. | H8: JwtService.java
A9: V9.2 | B9: Token content | C9: V9.2.3 | D9: Verify that the service only accepts tokens which are intended for use with that service (audience). For JWTs, this can be achieved by validating the 'aud' claim against an allowlist defined in the service. | E9: 2 | F9: In Progress | G9: Audience validation is not implemented in Sprint 1. | H9: Sprint 1 limitations
A10: V9.2 | B10: Token content | C10: V9.2.4 | D10: Verify that, if a token issuer uses the same private key for issuing tokens to different audiences, the issued tokens contain an audience restriction that uniquely identifies the intended audiences. This will prevent a token from being reused with an unintended audience. If the audience identifier is dynamically provisioned, the token issuer must validate these audiences in order to make sure that they do not result in audience impersonation. | E10: 2 | F10: Not Applicable | G10: The application has a single internal token issuer/key context for Sprint 1. | H10: JwtService.java

Sheet V10 - OAuth and OIDC
A1: Section ID | B1: Section Name | C1: Req ID | D1: Description | E1: Level | F1: Status | G1: Observations | H1: Reference / Link
A2: V10.1 | B2: Generic OAuth and OIDC Security
A3: V10.1 | B3: Generic OAuth and OIDC Security | C3: V10.1.1 | D3: Verify that tokens are only sent to components that strictly need them. For example, when using a backend-for-frontend pattern for browser-based JavaScript applications, access and refresh tokens shall only be accessible for the backend. | E3: 2 | F3: Not Applicable | G3: OAuth2/OIDC is not used. Authentication is internal JWT Bearer authentication. | H3: SecurityConfig.java; JwtService.java
A4: V10.1 | B4: Generic OAuth and OIDC Security | C4: V10.1.2 | D4: Verify that the client only accepts values from the authorization server (such as the authorization code or ID Token) if these values result from an authorization flow that was initiated by the same user agent session and transaction. This requires that client-generated secrets, such as the proof key for code exchange (PKCE) 'code_verifier', 'state' or OIDC 'nonce', are not guessable, are specific to the transaction, and are securely bound to both the client and the user agent session in which the transaction was started. | E4: 2 | F4: Not Applicable | G4: Application does not use OAuth2 or OpenID Connect; authentication is handled internally via backend-managed sessions and RBAC. | H4: DESOFS Phase 1: §5.1 RS1-RS3; §2.2 Assumptions
A5: V10.2 | B5: OAuth Client
A6: V10.2 | B6: OAuth Client | C6: V10.2.1 | D6: Verify that, if the code flow is used, the OAuth client has protection against browser-based request forgery attacks, commonly known as cross-site request forgery (CSRF), which trigger token requests, either by using proof key for code exchange (PKCE) functionality or checking the 'state' parameter that was sent in the authorization request. | E6: 2 | F6: Not Applicable | G6: Application does not use OAuth2 or OpenID Connect; authentication is handled internally via backend-managed sessions and RBAC. | H6: DESOFS Phase 1: §5.1 RS1-RS3; §2.2 Assumptions
A7: V10.2 | B7: OAuth Client | C7: V10.2.2 | D7: Verify that, if the OAuth client can interact with more than one authorization server, it has a defense against mix-up attacks. For example, it could require that the authorization server return the 'iss' parameter value and validate it in the authorization response and the token response. | E7: 2 | F7: Not Applicable | G7: Application does not use OAuth2 or OpenID Connect; authentication is handled internally via backend-managed sessions and RBAC. | H7: DESOFS Phase 1: §5.1 RS1-RS3; §2.2 Assumptions
A8: V10.2 | B8: OAuth Client | C8: V10.2.3 | D8: Verify that the OAuth client only requests the required scopes (or other authorization parameters) in requests to the authorization server. | E8: 3 | F8: Not Applicable | G8: Application does not use OAuth2 or OpenID Connect; authentication is handled internally via backend-managed sessions and RBAC. | H8: DESOFS Phase 1: §5.1 RS1-RS3; §2.2 Assumptions
A9: V10.3 | B9: OAuth Resource Server
A10: V10.3 | B10: OAuth Resource Server | C10: V10.3.1 | D10: Verify that the resource server only accepts access tokens that are intended for use with that service (audience). The audience may be included in a structured access token (such as the 'aud' claim in JWT), or it can be checked using the token introspection endpoint. | E10: 2 | F10: Not Applicable | G10: Application does not use OAuth2 or OpenID Connect; authentication is handled internally via backend-managed sessions and RBAC. | H10: DESOFS Phase 1: §5.1 RS1-RS3; §2.2 Assumptions
A11: V10.3 | B11: OAuth Resource Server | C11: V10.3.2 | D11: Verify that the resource server enforces authorization decisions based on claims from the access token that define delegated authorization. If claims such as 'sub', 'scope', and 'authorization_details' are present, they must be part of the decision. | E11: 2 | F11: Not Applicable | G11: Application does not use OAuth2 or OpenID Connect; authentication is handled internally via backend-managed sessions and RBAC. | H11: DESOFS Phase 1: §5.1 RS1-RS3; §2.2 Assumptions
A12: V10.3 | B12: OAuth Resource Server | C12: V10.3.3 | D12: Verify that if an access control decision requires identifying a unique user from an access token (JWT or related token introspection response), the resource server identifies the user from claims that cannot be reassigned to other users. Typically, it means using a combination of 'iss' and 'sub' claims. | E12: 2 | F12: Not Applicable | G12: Application does not use OAuth2 or OpenID Connect; authentication is handled internally via backend-managed sessions and RBAC. | H12: DESOFS Phase 1: §5.1 RS1-RS3; §2.2 Assumptions
A13: V10.3 | B13: OAuth Resource Server | C13: V10.3.4 | D13: Verify that, if the resource server requires specific authentication strength, methods, or recentness, it verifies that the presented access token satisfies these constraints. For example, if present, using the OIDC 'acr', 'amr' and 'auth_time' claims respectively. | E13: 2 | F13: Not Applicable | G13: Application does not use OAuth2 or OpenID Connect; authentication is handled internally via backend-managed sessions and RBAC. | H13: DESOFS Phase 1: §5.1 RS1-RS3; §2.2 Assumptions
A14: V10.3 | B14: OAuth Resource Server | C14: V10.3.5 | D14: Verify that the resource server prevents the use of stolen access tokens or replay of access tokens (from unauthorized parties) by requiring sender-constrained access tokens, either Mutual TLS for OAuth 2 or OAuth 2 Demonstration of Proof of Possession (DPoP). | E14: 3 | F14: Not Applicable | G14: Application does not use OAuth2 or OpenID Connect; authentication is handled internally via backend-managed sessions and RBAC. | H14: DESOFS Phase 1: §5.1 RS1-RS3; §2.2 Assumptions
A15: V10.4 | B15: OAuth Authorization Server
A16: V10.4 | B16: OAuth Authorization Server | C16: V10.4.1 | D16: Verify that the authorization server validates redirect URIs based on a client-specific allowlist of pre-registered URIs using exact string comparison. | E16: 1 | F16: Not Applicable | G16: Application does not use OAuth2 or OpenID Connect; authentication is handled internally via backend-managed sessions and RBAC. | H16: DESOFS Phase 1: §5.1 RS1-RS3; §2.2 Assumptions
A17: V10.4 | B17: OAuth Authorization Server | C17: V10.4.2 | D17: Verify that, if the authorization server returns the authorization code in the authorization response, it can be used only once for a token request. For the second valid request with an authorization code that has already been used to issue an access token, the authorization server must reject a token request and revoke any issued tokens related to the authorization code. | E17: 1 | F17: Not Applicable | G17: Application does not use OAuth2 or OpenID Connect; authentication is handled internally via backend-managed sessions and RBAC. | H17: DESOFS Phase 1: §5.1 RS1-RS3; §2.2 Assumptions
A18: V10.4 | B18: OAuth Authorization Server | C18: V10.4.3 | D18: Verify that the authorization code is short-lived. The maximum lifetime can be up to 10 minutes for L1 and L2 applications and up to 1 minute for L3 applications. | E18: 1 | F18: Not Applicable | G18: Application does not use OAuth2 or OpenID Connect; authentication is handled internally via backend-managed sessions and RBAC. | H18: DESOFS Phase 1: §5.1 RS1-RS3; §2.2 Assumptions
A19: V10.4 | B19: OAuth Authorization Server | C19: V10.4.4 | D19: Verify that for a given client, the authorization server only allows the usage of grants that this client needs to use. Note that the grants 'token' (Implicit flow) and 'password' (Resource Owner Password Credentials flow) must no longer be used. | E19: 1 | F19: Not Applicable | G19: Application does not use OAuth2 or OpenID Connect; authentication is handled internally via backend-managed sessions and RBAC. | H19: DESOFS Phase 1: §5.1 RS1-RS3; §2.2 Assumptions
A20: V10.4 | B20: OAuth Authorization Server | C20: V10.4.5 | D20: Verify that the authorization server mitigates refresh token replay attacks for public clients, preferably using sender-constrained refresh tokens, i.e., Demonstrating Proof of Possession (DPoP) or Certificate-Bound Access Tokens using mutual TLS (mTLS). For L1 and L2 applications, refresh token rotation may be used. If refresh token rotation is used, the authorization server must invalidate the refresh token after usage, and revoke all refresh tokens for that authorization if an already used and invalidated refresh token is provided. | E20: 1 | F20: Not Applicable | G20: Application does not use OAuth2 or OpenID Connect; authentication is handled internally via backend-managed sessions and RBAC. | H20: DESOFS Phase 1: §5.1 RS1-RS3; §2.2 Assumptions
A21: V10.4 | B21: OAuth Authorization Server | C21: V10.4.6 | D21: Verify that, if the code grant is used, the authorization server mitigates authorization code interception attacks by requiring proof key for code exchange (PKCE). For authorization requests, the authorization server must require a valid 'code_challenge' value and must not accept a 'code_challenge_method' value of 'plain'. For a token request, it must require validation of the 'code_verifier' parameter. | E21: 2 | F21: Not Applicable | G21: Application does not use OAuth2 or OpenID Connect; authentication is handled internally via backend-managed sessions and RBAC. | H21: DESOFS Phase 1: §5.1 RS1-RS3; §2.2 Assumptions
A22: V10.4 | B22: OAuth Authorization Server | C22: V10.4.7 | D22: Verify that if the authorization server supports unauthenticated dynamic client registration, it mitigates the risk of malicious client applications. It must validate client metadata such as any registered URIs, ensure the user's consent, and warn the user before processing an authorization request with an untrusted client application. | E22: 2 | F22: Not Applicable | G22: Application does not use OAuth2 or OpenID Connect; authentication is handled internally via backend-managed sessions and RBAC. | H22: DESOFS Phase 1: §5.1 RS1-RS3; §2.2 Assumptions
A23: V10.4 | B23: OAuth Authorization Server | C23: V10.4.8 | D23: Verify that refresh tokens have an absolute expiration, including if sliding refresh token expiration is applied. | E23: 2 | F23: Not Applicable | G23: Application does not use OAuth2 or OpenID Connect; authentication is handled internally via backend-managed sessions and RBAC. | H23: DESOFS Phase 1: §5.1 RS1-RS3; §2.2 Assumptions
A24: V10.4 | B24: OAuth Authorization Server | C24: V10.4.9 | D24: Verify that refresh tokens and reference access tokens can be revoked by an authorized user using the authorization server user interface, to mitigate the risk of malicious clients or stolen tokens. | E24: 2 | F24: Not Applicable | G24: Application does not use OAuth2 or OpenID Connect; authentication is handled internally via backend-managed sessions and RBAC. | H24: DESOFS Phase 1: §5.1 RS1-RS3; §2.2 Assumptions
A25: V10.4 | B25: OAuth Authorization Server | C25: V10.4.10 | D25: Verify that confidential client is authenticated for client-to-authorized server backchannel requests such as token requests, pushed authorization requests (PAR), and token revocation requests. | E25: 2 | F25: Not Applicable | G25: Application does not use OAuth2 or OpenID Connect; authentication is handled internally via backend-managed sessions and RBAC. | H25: DESOFS Phase 1: §5.1 RS1-RS3; §2.2 Assumptions
A26: V10.4 | B26: OAuth Authorization Server | C26: V10.4.11 | D26: Verify that the authorization server configuration only assigns the required scopes to the OAuth client. | E26: 2 | F26: Not Applicable | G26: Application does not use OAuth2 or OpenID Connect; authentication is handled internally via backend-managed sessions and RBAC. | H26: DESOFS Phase 1: §5.1 RS1-RS3; §2.2 Assumptions
A27: V10.4 | B27: OAuth Authorization Server | C27: V10.4.12 | D27: Verify that for a given client, the authorization server only allows the 'response_mode' value that this client needs to use. For example, by having the authorization server validate this value against the expected values or by using pushed authorization request (PAR) or JWT-secured Authorization Request (JAR). | E27: 3 | F27: Not Applicable | G27: Application does not use OAuth2 or OpenID Connect; authentication is handled internally via backend-managed sessions and RBAC. | H27: DESOFS Phase 1: §5.1 RS1-RS3; §2.2 Assumptions
... A31: V10.4 | B31: OAuth Authorization Server | C31: V10.4.16 | D31: Verify that the client is confidential and the authorization server requires the use of strong client authentication methods (based on public-key cryptography and resistant to replay attacks), such as mutual TLS ('tls_client_auth', 'self_signed_tls_client_auth') or private key JWT ('private_key_jwt'). | E31: 3 | F31: Not Applicable | G31: Application does not use OAuth2 or OpenID Connect; authentication is handled internally via backend-managed sessions and RBAC. | H31: DESOFS Phase 1: §5.1 RS1-RS3; §2.2 Assumptions
A32: V10.5 | B32: OIDC Client
A33: V10.5 | B33: OIDC Client | C33: V10.5.1 | D33: Verify that the client (as the relying party) mitigates ID Token replay attacks. For example, by ensuring that the 'nonce' claim in the ID Token matches the 'nonce' value sent in the authentication request to the OpenID Provider (in OAuth2 refereed to as the authorization request sent to the authorization server). | E33: 2 | F33: Not Applicable | G33: Application does not use OAuth2 or OpenID Connect; authentication is handled internally via backend-managed sessions and RBAC. | H33: DESOFS Phase 1: §5.1 RS1-RS3; §2.2 Assumptions
A34: V10.5 | B34: OIDC Client | C34: V10.5.2 | D34: Verify that the client uniquely identifies the user from ID Token claims, usually the 'sub' claim, which cannot be reassigned to other users (for the scope of an identity provider). | E34: 2 | F34: Not Applicable | G34: Application does not use OAuth2 or OpenID Connect; authentication is handled internally via backend-managed sessions and RBAC. | H34: DESOFS Phase 1: §5.1 RS1-RS3; §2.2 Assumptions
A35: V10.5 | B35: OIDC Client | C35: V10.5.3 | D35: Verify that the client rejects attempts by a malicious authorization server to impersonate another authorization server through authorization server metadata. The client must reject authorization server metadata if the issuer URL in the authorization server metadata does not exactly match the pre-configured issuer URL expected by the client. | E35: 2 | F35: Not Applicable | G35: Application does not use OAuth2 or OpenID Connect; authentication is handled internally via backend-managed sessions and RBAC. | H35: DESOFS Phase 1: §5.1 RS1-RS3; §2.2 Assumptions
A36: V10.5 | B36: OIDC Client | C36: V10.5.4 | D36: Verify that the client validates that the ID Token is intended to be used for that client (audience) by checking that the 'aud' claim from the token is equal to the 'client_id' value for the client. | E36: 2 | F36: Not Applicable | G36: Application does not use OAuth2 or OpenID Connect; authentication is handled internally via backend-managed sessions and RBAC. | H36: DESOFS Phase 1: §5.1 RS1-RS3; §2.2 Assumptions
A37: V10.5 | B37: OIDC Client | C37: V10.5.5 | D37: Verify that, when using OIDC back-channel logout, the relying party mitigates denial of service through forced logout and cross-JWT confusion in the logout flow. The client must verify that the logout token is correctly typed with a value of 'logout+jwt', contains the 'event' claim with the correct member name, and does not contain a 'nonce' claim. Note that it is also recommended to have a short expiration (e.g., 2 minutes). | E37: 2 | F37: Not Applicable | G37: Application does not use OAuth2 or OpenID Connect; authentication is handled internally via backend-managed sessions and RBAC. | H37: DESOFS Phase 1: §5.1 RS1-RS3; §2.2 Assumptions
A38: V10.6 | B38: OpenID Provider
A39: V10.6 | B39: OpenID Provider | C39: V10.6.1 | D39: Verify that the OpenID Provider only allows values 'code', 'ciba', 'id_token', or 'id_token code' for response mode. Note that 'code' is preferred over 'id_token code' (the OIDC Hybrid flow), and 'token' (any Implicit flow) must not be used. | E39: 2 | F39: Not Applicable | G39: Application does not use OAuth2 or OpenID Connect; authentication is handled internally via backend-managed sessions and RBAC. | H39: DESOFS Phase 1: §5.1 RS1-RS3; §2.2 Assumptions
A40: V10.6 | B40: OpenID Provider | C40: V10.6.2 | D40: Verify that the OpenID Provider mitigates denial of service through forced logout. By obtaining explicit confirmation from the end-user or, if present, validating parameters in the logout request (initiated by the relying party), such as the 'id_token_hint'. | E40: 2 | F40: Not Applicable | G40: Application does not use OAuth2 or OpenID Connect; authentication is handled internally via backend-managed sessions and RBAC. | H40: DESOFS Phase 1: §5.1 RS1-RS3; §2.2 Assumptions
A41: V10.7 | B41: Consent Management
A42: V10.7 | B42: Consent Management | C42: V10.7.1 | D42: Verify that the authorization server ensures that the user consents to each authorization request. If the identity of the client cannot be assured, the authorization server must always explicitly prompt the user for consent. | E42: 2 | F42: Not Applicable | G42: Application does not use OAuth2 or OpenID Connect; authentication is handled internally via backend-managed sessions and RBAC. | H42: DESOFS Phase 1: §5.1 RS1-RS3; §2.2 Assumptions
A43: V10.7 | B43: Consent Management | C43: V10.7.2 | D43: Verify that when the authorization server prompts for user consent, it presents sufficient and clear information about what is being consented to. When applicable, this should include the nature of the requested authorizations (typically based on scope, resource server, Rich Authorization Requests (RAR) authorization details), the identity of the authorized application, and the lifetime of these authorizations. | E43: 2 | F43: Not Applicable | G43: Application does not use OAuth2 or OpenID Connect; authentication is handled internally via backend-managed sessions and RBAC. | H43: DESOFS Phase 1: §5.1 RS1-RS3; §2.2 Assumptions
A44: V10.7 | B44: Consent Management | C44: V10.7.3 | D44: Verify that the user can review, modify, and revoke consents which the user has granted through the authorization server. | E44: 2 | F44: Not Applicable | G44: Application does not use OAuth2 or OpenID Connect; authentication is handled internally via backend-managed sessions and RBAC. | H44: DESOFS Phase 1: §5.1 RS1-RS3; §2.2 Assumptions

Sheet V11 - Cryptography
A1: Section ID | B1: Section Name | C1: Req ID | D1: Description | E1: Level | F1: Status | G1: Observations | H1: Reference / Link
A2: V11.1 | B2: Cryptographic Inventory and Documentation
A3: V11.1 | B3: Cryptographic Inventory and Documentation | C3: V11.1.1 | D3: Verify that there is a documented policy for management of cryptographic keys and a cryptographic key lifecycle that follows a key management standard such as NIST SP 800-57. This should include ensuring that keys are not overshared (for example, with more than two entities for shared secrets and more than one entity for private keys). | E3: 2 | F3: Not Started | G3: Cryptographic controls (hashing, TLS, token generation) are required by design, but specific algorithms, key management practices, and implementation details are not yet formally defined in Phase 1. | H3: DESOFS Phase 1: §5.3 RS8; §2.2 Assumptions (TLS); §11 hashing of codes/files
A4: V11.1 | B4: Cryptographic Inventory and Documentation | C4: V11.1.2 | D4: Verify that a cryptographic inventory is performed, maintained, regularly updated, and includes all cryptographic keys, algorithms, and certificates used by the application. It must also document where keys can and cannot be used in the system, and the types of data that can and cannot be protected using the keys. | E4: 2 | F4: Not Started | G4: Cryptographic controls (hashing, TLS, token generation) are required by design, but specific algorithms, key management practices, and implementation details are not yet formally defined in Phase 1. | H4: DESOFS Phase 1: §5.3 RS8; §2.2 Assumptions (TLS); §11 hashing of codes/files
A5: V11.1 | B5: Cryptographic Inventory and Documentation | C5: V11.1.3 | D5: Verify that cryptographic discovery mechanisms are employed to identify all instances of cryptography in the system, including encryption, hashing, and signing operations. | E5: 3 | F5: Not Started | G5: Cryptographic controls (hashing, TLS, token generation) are required by design, but specific algorithms, key management practices, and implementation details are not yet formally defined in Phase 1. | H5: DESOFS Phase 1: §5.3 RS8; §2.2 Assumptions (TLS); §11 hashing of codes/files
A6: V11.1 | B6: Cryptographic Inventory and Documentation | C6: V11.1.4 | D6: Verify that a cryptographic inventory is maintained. This must include a documented plan that outlines the migration path to new cryptographic standards, such as post-quantum cryptography, in order to react to future threats. | E6: 3 | F6: Not Started | G6: Cryptographic controls (hashing, TLS, token generation) are required by design, but specific algorithms, key management practices, and implementation details are not yet formally defined in Phase 1. | H6: DESOFS Phase 1: §5.3 RS8; §2.2 Assumptions (TLS); §11 hashing of codes/files
A7: V11.2 | B7: Secure Cryptography Implementation
A8: V11.2 | B8: Secure Cryptography Implementation | C8: V11.2.1 | D8: Verify that industry-validated implementations (including libraries and hardware-accelerated implementations) are used for cryptographic operations. | E8: 2 | F8: Compliant | G8: Cryptographic operations use platform/framework implementations: BCryptPasswordEncoder, SecureRandom, MessageDigest SHA-256 and HmacSHA256. | H8: SecurityConfig.java; TrackingCode.java; BackupService.java; CasePackageService.java; JwtService.java
A9: V11.2 | B9: Secure Cryptography Implementation | C9: V11.2.2 | D9: Verify that the application is designed with crypto agility such that random number, authenticated encryption, MAC, or hashing algorithms, key lengths, rounds, ciphers and modes can be reconfigured, upgraded, or swapped at any time, to protect against cryptographic breaks. Similarly, it must also be possible to replace keys and passwords and re-encrypt data. This will allow for seamless upgrades to post-quantum cryptography (PQC), once high-assurance implementations of approved PQC schemes or standards are widely available. | E9: 2 | F9: Not Started | G9: Strong cryptography is expected, but algorithm agility/bit-strength requirements are not yet written down. | H9: DESOFS Phase 1: §5.3 RS8; §2.2 Assumptions (TLS/HTTPS); §11 hashing of codes/files
A10: V11.2 | B10: Secure Cryptography Implementation | C10: V11.2.3 | D10: Verify that all cryptographic primitives utilize a minimum of 128-bits of security based on the algorithm, key size, and configuration. For example, a 256-bit ECC key provides roughly 128 bits of security where RSA requires a 3072-bit key to achieve 128 bits of security. | E10: 2 | F10: Not Started | G10: Strong cryptography is expected, but algorithm agility/bit-strength requirements are not yet written down. | H10: DESOFS Phase 1: §5.3 RS8; §2.2 Assumptions (TLS/HTTPS); §11 hashing of codes/files
A11: V11.2 | B11: Secure Cryptography Implementation | C11: V11.2.4 | D11: Verify that all cryptographic operations are constant-time, with no 'short-circuit' operations in comparisons, calculations, or returns, to avoid leaking information. | E11: 3 | F11: Not Started | G11: This is advanced crypto-hardening detail not yet covered in Phase 1 documentation. | H11: DESOFS Phase 1: §5.3 RS8; §11 hashing of codes/files; tokens with expiration
A12: V11.2 | B12: Secure Cryptography Implementation | C12: V11.2.5 | D12: Verify that all cryptographic modules fail securely, and errors are handled in a way that does not enable vulnerabilities, such as Padding Oracle attacks. | E12: 3 | F12: Not Started | G12: This is advanced crypto-hardening detail not yet covered in Phase 1 documentation. | H12: DESOFS Phase 1: §5.3 RS8; §2.2 Assumptions (TLS/HTTPS); §11 hashing of codes/files
A13: V11.3 | B13: Encryption Algorithms
A14: V11.3 | B14: Encryption Algorithms | C14: V11.3.1 | D14: Verify that insecure block modes (e.g., ECB) and weak padding schemes (e.g., PKCS#1 v1.5) are not used. | E14: 1 | F14: Compliant | G14: No custom block cipher modes are used in Sprint 1. | H14: Code review Sprint 1
A15: V11.3 | B15: Encryption Algorithms | C15: V11.3.2 | D15: Verify that only approved ciphers and modes such as AES with GCM are used. | E15: 1 | F15: Not Started | G15: Cryptographic primitives should be selected safely in implementation; exact algorithms are not yet specified. | H15: DESOFS Phase 1: §5.3 RS8; §2.2 Assumptions (HTTPS/TLS)
A16: V11.3 | B16: Encryption Algorithms | C16: V11.3.3 | D16: Verify that encrypted data is protected against unauthorized modification preferably by using an approved authenticated encryption method or by combining an approved encryption method with an approved MAC algorithm. | E16: 2 | F16: Not Started | G16: Cryptographic primitives should be selected safely in implementation; exact algorithms are not yet specified. | H16: DESOFS Phase 1: §5.3 RS8; §2.2 Assumptions (HTTPS/TLS)
A17: V11.3 | B17: Encryption Algorithms | C17: V11.3.4 | D17: Verify that nonces, initialization vectors, and other single-use numbers are not used for more than one encryption key and data-element pair. The method of generation must be appropriate for the algorithm being used. | E17: 3 | F17: Not Started | G17: This is advanced crypto-hardening detail not yet covered in Phase 1 documentation. | H17: DESOFS Phase 1: §5.3 RS8; §2.2 Assumptions (HTTPS/TLS)
A18: V11.3 | B18: Encryption Algorithms | C18: V11.3.5 | D18: Verify that any combination of an encryption algorithm and a MAC algorithm is operating in encrypt-then-MAC mode. | E18: 3 | F18: Not Started | G18: This is advanced crypto-hardening detail not yet covered in Phase 1 documentation. | H18: DESOFS Phase 1: §5.3 RS8; §2.2 Assumptions (HTTPS/TLS)
A19: V11.4 | B19: Hashing and Hash-based Functions
A20: V11.4 | B20: Hashing and Hash-based Functions | C20: V11.4.1 | D20: Verify that only approved hash functions are used for general cryptographic use cases, including digital signatures, HMAC, KDF, and random bit generation. Disallowed hash functions, such as MD5, must not be used for any cryptographic purpose. | E20: 1 | F20: Compliant | G20: Approved hash/MAC functions are used for current needs: SHA-256 for integrity/tracking hashes and HMAC-SHA256 for JWT signing. | H20: JwtService.java; ReportService.java; BackupService.java; CasePackageService.java
A21: V11.4 | B21: Hashing and Hash-based Functions | C21: V11.4.2 | D21: Verify that passwords are stored using an approved, computationally intensive, key derivation function (also known as a "password hashing function"), with parameter settings configured based on current guidance. The settings should balance security and performance to make brute-force attacks sufficiently challenging for the required level of security. | E21: 2 | F21: Not Started | G21: Passwords must not be stored in plaintext, but the exact approved password-hashing algorithm/parameters are still to be specified. | H21: DESOFS Phase 1: §5.3 RS8; §11 hashing of codes/files
A22: V11.4 | B22: Hashing and Hash-based Functions | C22: V11.4.3 | D22: Verify that hash functions used in digital signatures, as part of data authentication or data integrity are collision resistant and have appropriate bit-lengths. If collision resistance is required, the output length must be at least 256 bits. If only resistance to second pre-image attacks is required, the output length must be at least 128 bits. | E22: 2 | F22: Not Started | G22: Cryptographic primitives should be selected safely in implementation; exact algorithms are not yet specified. | H22: DESOFS Phase 1: §5.3 RS8; §11 hashing of codes/files
A23: V11.4 | B23: Hashing and Hash-based Functions | C23: V11.4.4 | D23: Verify that the application uses approved key derivation functions with key stretching parameters when deriving secret keys from passwords. The parameters in use must balance security and performance to prevent brute-force attacks from compromising the resulting cryptographic key. | E23: 2 | F23: Not Applicable | G23: Not applicable in the current system design. | H23: N/A – not in current system scope
A24: V11.5 | B24: Random Values
A25: V11.5 | B25: Random Values | C25: V11.5.1 | D25: Verify that all random numbers and strings which are intended to be non-guessable must be generated using a cryptographically secure pseudo-random number generator (CSPRNG) and have at least 128 bits of entropy. Note that UUIDs do not respect this condition. | E25: 2 | F25: Not Started | G25: Tracking codes and session material are intended to be unique, unpredictable, and high-entropy. | H25: DESOFS Phase 1: §5.3 RS8; §11 tokens/identifiers generation
A26: V11.5 | B26: Random Values | C26: V11.5.2 | D26: Verify that the random number generation mechanism in use is designed to work securely, even under heavy demand. | E26: 3 | F26: Not Started | G26: CSPRNG robustness under heavy load is not documented. | H26: DESOFS Phase 1: §5.3 RS8; §11 tokens/identifiers generation
A27: V11.6 | B27: Public Key Cryptography
A28: V11.6 | B28: Public Key Cryptography | C28: V11.6.1 | D28: Verify that only approved cryptographic algorithms and modes of operation are used for key generation and seeding, and digital signature generation and verification. Key generation algorithms must not generate insecure keys vulnerable to known attacks, for example, RSA keys which are vulnerable to Fermat factorization. | E28: 2 | F28: Not Started | G28: Cryptographic primitives should be selected safely in implementation; exact algorithms are not yet specified. | H28: DESOFS Phase 1: §5.3 RS8; §2.2 Assumptions (TLS/HTTPS)
A29: V11.6 | B29: Public Key Cryptography | C29: V11.6.2 | D29: Verify that approved cryptographic algorithms are used for key exchange (such as Diffie-Hellman) with a focus on ensuring that key exchange mechanisms use secure parameters. This will prevent attacks on the key establishment process which could lead to adversary-in-the-middle attacks or cryptographic breaks. | E29: 3 | F29: Not Started | G29: This is advanced crypto-hardening detail not yet covered in Phase 1 documentation. | H29: DESOFS Phase 1: §5.3 RS8; §2.2 Assumptions (TLS/HTTPS)
A30: V11.7 | B30: In-Use Data Cryptography
A31: V11.7 | B31: In-Use Data Cryptography | C31: V11.7.1 | D31: Verify that full memory encryption is in use that protects sensitive data while it is in use, preventing access by unauthorized users or processes. | E31: 3 | F31: Not Started | G31: This is advanced crypto-hardening detail not yet covered in Phase 1 documentation. | H31: DESOFS Phase 1: §5.2 RS4-RS6
A32: V11.7 | B32: In-Use Data Cryptography | C32: V11.7.2 | D32: Verify that data minimization ensures the minimal amount of data is exposed during processing, and ensure that data is encrypted immediately after use or as soon as feasible. | E32: 3 | F32: Not Started | G32: Data minimization is explicit, but immediate encryption-after-use processing detail is not yet documented. | H32: DESOFS Phase 1: §5.2 RS4-RS6

Sheet V12 - Secure Communication
A1: Section ID | B1: Section Name | C1: Req ID | D1: Description | E1: Level | F1: Status | G1: Observations | H1: Reference / Link
A2: V12.1 | B2: General TLS Security Guidance
A3: V12.1 | B3: General TLS Security Guidance | C3: V12.1.1 | D3: Verify that only the latest recommended versions of the TLS protocol are enabled, such as TLS 1.2 and TLS 1.3. The latest version of the TLS protocol must be the preferred option. | E3: 1 | F3: In Progress | G3: HTTPS/TLS is assumed in deployment requirements, but the Sprint 1 local application does not configure TLS versions directly. | H3: Phase 1 assumptions; Sprint 1 deployment limitations
A4: V12.1 | B4: General TLS Security Guidance | C4: V12.1.2 | D4: Verify that only recommended cipher suites are enabled, with the strongest cipher suites set as preferred. L3 applications must only support cipher suites which provide forward secrecy. | E4: 2 | F4: Not Started | G4: Cipher-suite policy is not yet specified. | H4: DESOFS Phase 1: assumptions §2.2 HTTPS; §5.3 RS7; AC9/AC10
A5: V12.1 | B5: General TLS Security Guidance | C5: V12.1.3 | D5: Verify that the application validates that mTLS client certificates are trusted before using the certificate identity for authentication or authorization. | E5: 2 | F5: Not Applicable | G5: Not applicable – the current design does not use mutual TLS client certificates for authentication or authorization. | H5: N/A – mTLS client authentication not in current system scope
A6: V12.1 | B6: General TLS Security Guidance | C6: V12.1.4 | D6: Verify that proper certification revocation, such as Online Certificate Status Protocol (OCSP) Stapling, is enabled and configured. | E6: 3 | F6: Not Started | G6: Advanced TLS features such as OCSP stapling and ECH are not required for Phase 1 and are not yet specified in the deployment configuration. | H6: DESOFS Phase 1: assumptions §2.2 HTTPS; §5.3 RS7; AC9/AC10
A7: V12.1 | B7: General TLS Security Guidance | C7: V12.1.5 | D7: Verify that Encrypted Client Hello (ECH) is enabled in the application's TLS settings to prevent exposure of sensitive metadata, such as the Server Name Indication (SNI), during TLS handshake processes. | E7: 3 | F7: Not Started | G7: Advanced TLS features such as OCSP stapling and ECH are not required for Phase 1 and are not yet specified in the deployment configuration. | H7: DESOFS Phase 1: assumptions §2.2 HTTPS; §5.3 RS7; AC9/AC10
A8: V12.2 | B8: HTTPS Communication with External Facing Services
A9: V12.2 | B9: HTTPS Communication with External Facing Services | C9: V12.2.1 | D9: Verify that TLS is used for all connectivity between a client and external facing, HTTP-based services, and does not fall back to insecure or unencrypted communications. | E9: 1 | F9: In Progress | G9: HTTPS is required by design for external deployment, but Sprint 1 CI/local evidence runs over HTTP. | H9: Phase 1 assumptions; ZAP baseline target
A10: V12.2 | B10: HTTPS Communication with External Facing Services | C10: V12.2.2 | D10: Verify that external facing services use publicly trusted TLS certificates. | E10: 1 | F10: Not Started | G10: Production certificate sourcing/trust model is still an implementation detail. | H10: DESOFS Phase 1: assumptions §2.2 HTTPS; §5.3 RS7; AC9/AC10
A11: V12.3 | B11: General Service to Service Communication Security
A12: V12.3 | B12: General Service to Service Communication Security | C12: V12.3.1 | D12: Verify that an encrypted protocol such as TLS is used for all inbound and outbound connections to and from the application, including monitoring systems, management tools, remote access and SSH, middleware, databases, mainframes, partner systems, or external APIs. The server must not fall back to insecure or unencrypted protocols. | E12: 2 | F12: Not Started | G12: Service-to-service encryption and certificate validation are required by design, but detailed configuration (e.g., TLS enforcement, certificate trust model, internal CA usage) is not yet defined and will be specified during deployment architecture. | H12: DESOFS Phase 1: §2.2 HTTPS; §5.3 RS7; §9 trust boundaries; STRIDE T/M
A13: V12.3 | B13: General Service to Service Communication Security | C13: V12.3.2 | D13: Verify that TLS clients validate certificates received before communicating with a TLS server. | E13: 2 | F13: Not Started | G13: Service-to-service encryption and certificate validation are required by design, but detailed configuration (e.g., TLS enforcement, certificate trust model, internal CA usage) is not yet defined and will be specified during deployment architecture. | H13: DESOFS Phase 1: §2.2 HTTPS; §5.3 RS7; §9 trust boundaries; STRIDE T/M
A14: V12.3 | B14: General Service to Service Communication Security | C14: V12.3.3 | D14: Verify that TLS or another appropriate transport encryption mechanism used for all connectivity between internal, HTTP-based services within the application, and does not fall back to insecure or unencrypted communications. | E14: 2 | F14: Not Started | G14: Service-to-service encryption and certificate validation are required by design, but detailed configuration (e.g., TLS enforcement, certificate trust model, internal CA usage) is not yet defined and will be specified during deployment architecture. | H14: DESOFS Phase 1: §2.2 HTTPS; §5.3 RS7; §9 trust boundaries; STRIDE T/M
A15: V12.3 | B15: General Service to Service Communication Security | C15: V12.3.4 | D15: Verify that TLS connections between internal services use trusted certificates. Where internally generated or self-signed certificates are used, the consuming service must be configured to only trust specific internal CAs and specific self-signed certificates. | E15: 2 | F15: Not Started | G15: Service-to-service encryption and certificate validation are required by design, but detailed configuration (e.g., TLS enforcement, certificate trust model, internal CA usage) is not yet defined and will be specified during deployment architecture. | H15: DESOFS Phase 1: §2.2 HTTPS; §5.3 RS7; §9 trust boundaries; STRIDE T/M
A16: V12.3 | B16: General Service to Service Communication Security | C16: V12.3.5 | D16: Verify that services communicating internally within a system (intra-service communications) use strong authentication to ensure that each endpoint is verified. Strong authentication methods, such as TLS client authentication, must be employed to ensure identity, using public-key infrastructure and mechanisms that are resistant to replay attacks. For microservice architectures, consider using a service mesh to simplify certificate management and enhance security. | E16: 3 | F16: Not Applicable | G16: Not applicable in Phase 1, as the system does not use a microservices architecture or mutual TLS authentication between services. | H16: N/A – service mesh/mTLS not in current system scope

Sheet V13 - Configuration
A1: Section ID | B1: Section Name | C1: Req ID | D1: Description | E1: Level | F1: Status | G1: Observations | H1: Reference / Link
A2: V13.1 | B2: Configuration Documentation
A3: V13.1 | B3: Configuration Documentation | C3: V13.1.1 | D3: Verify that all communication needs for the application are documented. This must include external services which the application relies upon and cases where an end user might be able to provide an external location to which the application will then connect. | E3: 2 | F3: Compliant | G3: Core communication paths are documented: browser/static frontend, REST API, PostgreSQL, local file storage and GitHub Actions service container. | H3: Sprint 1 report ?2, ?11
A4: V13.1 | B4: Configuration Documentation | C4: V13.1.2 | D4: Verify that for each service the application uses, the documentation defines the maximum number of concurrent connections (e.g., connection pool limits) and how the application behaves when that limit is reached, including any fallback or recovery mechanisms, to prevent denial of service conditions. | E4: 3 | F4: Not Started | G4: Detailed configuration parameters such as connection limits, timeout/retry strategies, and secret lifecycle/rotation policies are not yet formally defined and will be specified during implementation and deployment design. | H4: DESOFS Phase 1: DFD/trust boundaries §9; STRIDE §10; mitigations §11
A5: V13.1 | B5: Configuration Documentation | C5: V13.1.3 | D5: Verify that the application documentation defines resource‑management strategies for every external system or service it uses (e.g., databases, file handles, threads, HTTP connections). This should include resource‑release procedures, timeout settings, failure handling, and where retry logic is implemented, specifying retry limits, delays, and back‑off algorithms. For synchronous HTTP request–response operations it should mandate short timeouts and either disable retries or strictly limit retries to prevent cascading delays and resource exhaustion. | E5: 3 | F5: Not Started | G5: Detailed configuration parameters such as connection limits, timeout/retry strategies, and secret lifecycle/rotation policies are not yet formally defined and will be specified during implementation and deployment design. | H5: DESOFS Phase 1: DFD/trust boundaries §9; STRIDE §10; mitigations §11
A6: V13.1 | B6: Configuration Documentation | C6: V13.1.4 | D6: Verify that the application's documentation defines the secrets that are critical for the security of the application and a schedule for rotating them, based on the organization's threat model and business requirements. | E6: 3 | F6: In Progress | G6: Critical secrets are identified as environment/configuration values such as JWT_SECRET, DB credentials and NVD_API_KEY. Formal lifecycle/rotation policy is not complete. | H6: application.yaml; GitHub Actions secrets
A7: V13.2 | B7: Backend Communication Configuration
A8: V13.2 | B8: Backend Communication Configuration | C8: V13.2.1 | D8: Verify that communications between backend application components that don't support the application's standard user session mechanism, including APIs, middleware, and data layers, are authenticated. Authentication must use individual service accounts, short-term tokens, or certificate-based authentication and not unchanging credentials such as passwords, API keys, or shared accounts with privileged access. | E8: 2 | F8: Not Started | G8: Service-to-service authentication is expected to use least-privilege credentials (e.g., scoped tokens or service accounts), but the exact authentication mechanisms and credential lifecycle are not yet defined. | H8: DESOFS Phase 1: §9 trust boundaries; §10 STRIDE (T/S); §11 mitigations
A9: V13.2 | B9: Backend Communication Configuration | C9: V13.2.2 | D9: Verify that communications between backend application components, including local or operating system services, APIs, middleware, and data layers, are performed with accounts assigned the least necessary privileges. | E9: 2 | F9: Not Started | G9: Least-privilege service credentials align with the design but are not yet specified in detail. | H9: DESOFS Phase 1: §9 trust boundaries; §10 STRIDE (T/S); §11 mitigations
A10: V13.2 | B10: Backend Communication Configuration | C10: V13.2.3 | D10: Verify that if a credential has to be used for service authentication, the credential being used by the consumer is not a default credential (e.g., root/root or admin/admin). | E10: 2 | F10: Not Started | G10: Least-privilege service credentials align with the design but are not yet specified in detail. | H10: DESOFS Phase 1: §9 trust boundaries; §10 STRIDE (T/S); §11 mitigations
A11: V13.2 | B11: Backend Communication Configuration | C11: V13.2.4 | D11: Verify that an allowlist is used to define the external resources or systems with which the application is permitted to communicate (e.g., for outbound requests, data loads, or file access). This allowlist can be implemented at the application layer, web server, firewall, or a combination of different layers. | E11: 2 | F11: Not Started | G11: Outbound/network/file-access allowlists would strengthen SSRF and egress control but are not yet documented. | H11: DESOFS Phase 1: §9 trust boundaries; §10 STRIDE (T/S); §11 mitigations
A12: V13.2 | B12: Backend Communication Configuration | C12: V13.2.5 | D12: Verify that the web or application server is configured with an allowlist of resources or systems to which the server can send requests or load data or files from. | E12: 2 | F12: Not Started | G12: Outbound/network/file-access allowlists would strengthen SSRF and egress control but are not yet documented. | H12: DESOFS Phase 1: §9 trust boundaries; §10 STRIDE (T/S); §11 mitigations
A13: V13.2 | B13: Backend Communication Configuration | C13: V13.2.6 | D13: Verify that where the application connects to separate services, it follows the documented configuration for each connection, such as maximum parallel connections, behavior when maximum allowed connections is reached, connection timeouts, and retry strategies. | E13: 3 | F13: Not Started | G13: Connection pool/timeout behavior for external services is not yet specified. | H13: DESOFS Phase 1: §9 trust boundaries; §10 STRIDE (T/S); §11 mitigations
A14: V13.3 | B14: Secret Management
A15: V13.3 | B15: Secret Management | C15: V13.3.1 | D15: Verify that a secrets management solution, such as a key vault, is used to securely create, store, control access to, and destroy backend secrets. These could include passwords, key material, integrations with databases and third-party systems, keys and seeds for time-based tokens, other internal secrets, and API keys. Secrets must not be included in application source code or included in build artifacts. For an L3 application, this must involve a hardware-backed solution such as an HSM. | E15: 2 | F15: In Progress | G15: GitHub Actions secrets are used for CI secrets such as NVD_API_KEY and JWT_SECRET, but no dedicated production vault is implemented. | H15: GitHub repository secrets; workflows
A16: V13.3 | B16: Secret Management | C16: V13.3.2 | D16: Verify that access to secret assets adheres to the principle of least privilege. | E16: 2 | F16: In Progress | G16: Secrets are consumed through environment variables/configuration. Fine-grained production secret access policy remains future work. | H16: application.yaml; workflows
A17: V13.3 | B17: Secret Management | C17: V13.3.3 | D17: Verify that all cryptographic operations are performed using an isolated security module (such as a vault or hardware security module) to securely manage and protect key material from exposure outside of the security module. | E17: 3 | F17: Not Started | G17: Use of secure key management (e.g., vault or HSM) is not yet defined and depends on deployment architecture. | H17: DESOFS Phase 1: DFD/trust boundaries §9; STRIDE §10; mitigations §11
A18: V13.3 | B18: Secret Management | C18: V13.3.4 | D18: Verify that secrets are configured to expire and be rotated based on the application's documentation. | E18: 3 | F18: Not Started | G18: Secrets-management approach should be documented before deployment/implementation. | H18: DESOFS Phase 1: DFD/trust boundaries §9; STRIDE §10; mitigations §11
A19: V13.4 | B19: Unintended Information Leakage
A20: V13.4 | B20: Unintended Information Leakage | C20: V13.4.1 | D20: Verify that the application is deployed either without any source control metadata, including the .git or .svn folders, or in a way that these folders are inaccessible both externally and to the application itself. | E20: 1 | F20: In Progress | G20: CI builds from source and does not deploy a production artifact in Sprint 1; deployment hardening is future work. | H20: GitHub Actions workflows
A21: V13.4 | B21: Unintended Information Leakage | C21: V13.4.2 | D21: Verify that debug modes are disabled for all components in production environments to prevent exposure of debugging features and information leakage. | E21: 2 | F21: In Progress | G21: Dev/test profiles are separated and seed users are profile-scoped; full production hardening remains future work. | H21: application-dev.yaml; application-test.yaml; DataInitializer.java
A22: V13.4 | B22: Unintended Information Leakage | C22: V13.4.3 | D22: Verify that web servers do not expose directory listings to clients unless explicitly intended. | E22: 2 | F22: Compliant | G22: The Spring Boot/Tomcat application does not expose directory listings for controlled storage or static resources. | H22: Application behavior; FileStorageService.java
A23: V13.4 | B23: Unintended Information Leakage | C23: V13.4.4 | D23: Verify that using the HTTP TRACE method is not supported in production environments, to avoid potential information leakage. | E23: 2 | F23: Not Started | G23: Web-server method hardening (e.g., TRACE disabled) remains to be configured. | H23: DESOFS Phase 1: deployment assumptions; §9 architecture; §12 tests
A24: V13.4 | B24: Unintended Information Leakage | C24: V13.4.5 | D24: Verify that documentation (such as for internal APIs) and monitoring endpoints are not exposed unless explicitly intended. | E24: 2 | F24: Not Started | G24: Documentation/monitoring endpoint exposure rules are not yet specified. | H24: DESOFS Phase 1: RNF4-RNF5; §5.5 RS12-RS13; AC12; STRIDE D3/P7; §12 tests
A25: V13.4 | B25: Unintended Information Leakage | C25: V13.4.6 | D25: Verify that the application does not expose detailed version information of backend components. | E25: 3 | F25: Not Started | G25: Backend version disclosure control is not yet documented. | H25: DESOFS Phase 1: deployment assumptions; §9 architecture; §12 tests
A26: V13.4 | B26: Unintended Information Leakage | C26: V13.4.7 | D26: Verify that the web tier is configured to only serve files with specific file extensions to prevent unintentional information, configuration, and source code leakage. | E26: 3 | F26: Not Started | G26: Restricting served file types is aligned with preventing unintended exposure, but specific web-server configuration is not yet defined. | H26: DESOFS Phase 1: RF2/RF7/RF8; §5.4 RS9-RS11; AC3/AC6/AC7; STRIDE P2/P3; §12 tests

Sheet V14 - Data Protection
A1: Section ID | B1: Section Name | C1: Req ID | D1: Description | E1: Level | F1: Status | G1: Observations | H1: Reference / Link
A2: V14.1 | B2: Data Protection Documentation
A3: V14.1 | B3: Data Protection Documentation | C3: V14.1.1 | D3: Verify that all sensitive data created and processed by the application has been identified and classified into protection levels. This includes data that is only encoded and therefore easily decoded, such as Base64 strings or the plaintext payload inside a JWT. Protection levels need to take into account any data protection and privacy regulations and standards which the application is required to comply with. | E3: 2 | F3: In Progress | G3: Sensitive assets are identified in Phase 1 and Sprint 1 report, including reports, tracking codes, attachments, audit logs, users and backups. Formal data classification matrix remains future work. | H3: Phase 1 report; Sprint 1 report ?12
A4: V14.1 | B4: Data Protection Documentation | C4: V14.1.2 | D4: Verify that all sensitive data protection levels have a documented set of protection requirements. This must include (but not be limited to) requirements related to general encryption, integrity verification, retention, how the data is to be logged, access controls around sensitive data in logs, database-level encryption, privacy and privacy-enhancing technologies to be used, and other confidentiality requirements. | E4: 2 | F4: In Progress | G4: Protection goals are defined, but formal classification levels and detailed retention/logging requirements are not yet fully documented. | H4: DESOFS Phase 1: §5.2 RS4-RS6; §9 data flows; STRIDE I/P
A5: V14.2 | B5: General Data Protection
A6: V14.2 | B6: General Data Protection | C6: V14.2.1 | D6: Verify that sensitive data is only sent to the server in the HTTP message body or header fields, and that the URL and query string do not contain sensitive information, such as an API key or session token. | E6: 1 | F6: Compliant | G6: Tracking verification and secure download use request bodies/form-data rather than exposing tracking codes in URL query strings for the main API flows. | H6: ReportController.java; DTOs
A7: V14.2 | B7: General Data Protection | C7: V14.2.2 | D7: Verify that the application prevents sensitive data from being cached in server components, such as load balancers and application caches, or ensures that the data is securely purged after use. | E7: 2 | F7: Not Started | G7: Sensitive responses must include anti-caching controls (e.g., Cache-Control: no-store), but the exact header configuration is not yet defined. | H7: DESOFS Phase 1: §5.2 RS4-RS6; AC1/AC2; STRIDE I/P; §12 tests
A8: V14.2 | B8: General Data Protection | C8: V14.2.3 | D8: Verify that defined sensitive data is not sent to untrusted parties (e.g., user trackers) to prevent unwanted collection of data outside of the application's control. | E8: 2 | F8: In Progress | G8: No third-party trackers or untrusted external data sinks are part of the backend design. | H8: DESOFS Phase 1: §5.2 RS4-RS6; AC1/AC2; STRIDE P1/P4; §12 tests
A9: V14.2 | B9: General Data Protection | C9: V14.2.4 | D9: Verify that controls around sensitive data related to encryption, integrity verification, retention, how the data is to be logged, access controls around sensitive data in logs, privacy and privacy-enhancing technologies, are implemented as defined in the documentation for the specific data's protection level. | E9: 2 | F9: In Progress | G9: Integrity and access controls exist for evidence and backups. Retention/encryption policies remain future work. | H9: BackupService.java; CasePackageService.java; Sprint 1 limitations
A10: V14.2 | B10: General Data Protection | C10: V14.2.5 | D10: Verify that caching mechanisms are configured to only cache responses which have the expected content type for that resource and do not contain sensitive, dynamic content. The web server should return a 404 or 302 response when a non-existent file is accessed rather than returning a different, valid file. This should prevent Web Cache Deception attacks. | E10: 3 | F10: Not Started | G10: Specific protections against web cache deception attacks are not yet defined in the web/server configuration. | H10: DESOFS Phase 1: §5.2 RS4-RS6; AC1/AC2; STRIDE I/P; §12 tests
A11: V14.2 | B11: General Data Protection | C11: V14.2.6 | D11: Verify that the application only returns the minimum required sensitive data for the application's functionality. For example, only returning some of the digits of a credit card number and not the full number. If the complete data is required, it should be masked in the user interface unless the user specifically views it. | E11: 3 | F11: In Progress | G11: DTO responses reduce direct entity exposure. Additional review of all response fields can further minimize returned data. | H11: DTO package; Sprint 1 report ?5
A12: V14.2 | B12: General Data Protection | C12: V14.2.7 | D12: Verify that sensitive information is subject to data retention classification, ensuring that outdated or unnecessary data is deleted automatically, on a defined schedule, or as the situation requires. | E12: 3 | F12: Not Started | G12: Retention and deletion policies are required but not yet formally defined or automated. | H12: DESOFS Phase 1: §5.2 RS4-RS6; AC1/AC2; STRIDE P1; §12 tests
A13: V14.2 | B13: General Data Protection | C13: V14.2.8 | D13: Verify that sensitive information is removed from the metadata of user-submitted files unless storage is consented to by the user. | E13: 3 | F13: In Progress | G13: Filenames are sanitized and internal storage names are generated, but full metadata stripping for uploaded files is not implemented. | H13: FileStorageService.java; Sprint 1 limitations
A14: V14.3 | B14: Client-side Data Protection
A15: V14.3 | B15: Client-side Data Protection | C15: V14.3.1 | D15: Verify that authenticated data is cleared from client storage, such as the browser DOM, after the client or session is terminated. The 'Clear-Site-Data' HTTP response header field may be able to help with this but the client-side should also be able to clear up if the server connection is not available when the session is terminated. | E15: 1 | F15: Not Applicable | G15: Not applicable in Phase 1, as the system does not include a browser-based client storing authenticated data. | H15: N/A – frontend/browser functionality not in current system scope
A16: V14.3 | B16: Client-side Data Protection | C16: V14.3.2 | D16: Verify that the application sets sufficient anti-caching HTTP response header fields (i.e., Cache-Control: no-store) so that sensitive data is not cached in browsers. | E16: 2 | F16: Not Started | G16: Client-side data protection mechanisms (cache-control headers, storage policies, and token handling) are not yet defined and will be specified if a browser-based UI is introduced. | H16: DESOFS Phase 1: §5.2 RS4-RS6; AC1/AC2; STRIDE I/P; §12 tests
A17: V14.3 | B17: Client-side Data Protection | C17: V14.3.3 | D17: Verify that data stored in browser storage (such as localStorage, sessionStorage, IndexedDB, or cookies) does not contain sensitive data, with the exception of session tokens. | E17: 2 | F17: Not Started | G17: Client-side data protection mechanisms (cache-control headers, storage policies, and token handling) are not yet defined and will be specified if a browser-based UI is introduced. | H17: DESOFS Phase 1: §5.2 RS4-RS6; AC1/AC2; STRIDE P1/P4; §12 tests

Sheet V15 - Secure Coding and Archite
A1: Section ID | B1: Section Name | C1: Req ID | D1: Description | E1: Level | F1: Status | G1: Observations | H1: Reference / Link
A2: V15.1 | B2: Secure Coding and Architecture Documentation
A3: V15.1 | B3: Secure Coding and Architecture Documentation | C3: V15.1.1 | D3: Verify that application documentation defines risk based remediation time frames for 3rd party component versions with vulnerabilities and for updating libraries in general, to minimize the risk from these components. | E3: 1 | F3: In Progress | G3: Dependency-Check SCA is integrated and reports vulnerable components, but formal remediation SLAs are not yet defined. | H3: sca-dependency-check.yml; dependency-check reports
A4: V15.1 | B4: Secure Coding and Architecture Documentation | C4: V15.1.2 | D4: Verify that an inventory catalog, such as software bill of materials (SBOM), is maintained of all third-party libraries in use, including verifying that components come from pre-defined, trusted, and continually maintained repositories. | E4: 2 | F4: In Progress | G4: Dependency inventory is available through Maven and Dependency-Check reports. A formal SBOM is not yet maintained. | H4: pom.xml; dependency-check reports
A5: V15.1 | B5: Secure Coding and Architecture Documentation | C5: V15.1.3 | D5: Verify that the application documentation identifies functionality which is time-consuming or resource-demanding. This must include how to prevent a loss of availability due to overusing this functionality and how to avoid a situation where building a response takes longer than the consumer's timeout. Potential defenses may include asynchronous processing, using queues, and limiting parallel processes per user and per application. | E5: 2 | F5: In Progress | G5: Resource-intensive functionality (uploads, document generation, storage use) and anti-DoS mitigations are documented. | H5: DESOFS Phase 1: §9 trust boundaries; §10 STRIDE; §11 mitigations
A6: V15.1 | B6: Secure Coding and Architecture Documentation | C6: V15.1.4 | D6: Verify that application documentation highlights third-party libraries which are considered to be "risky components". | E6: 3 | F6: Not Started | G6: No high-risk third-party libraries have been identified yet; this requires dependency analysis and vulnerability scanning. | H6: Project.pdf: backend API, 3 roles, OS/file ops, ASVS deliverable
A7: V15.1 | B7: Secure Coding and Architecture Documentation | C7: V15.1.5 | D7: Verify that application documentation highlights parts of the application where "dangerous functionality" is being used. | E7: 3 | F7: In Progress | G7: Dangerous functionality is explicitly highlighted, particularly server-side file handling and document generation. | H7: DESOFS Phase 1: RF2/RF7/RF8; §5.4 RS9-RS11; STRIDE P/T; §12 tests
A8: V15.2 | B8: Security Architecture and Dependencies
A9: V15.2 | B9: Security Architecture and Dependencies | C9: V15.2.1 | D9: Verify that the application only contains components which have not breached the documented update and remediation time frames. | E9: 1 | F9: In Progress | G9: SCA reports currently run in evidence mode and identified CVEs must be triaged before enforcing update gates. | H9: Dependency-Check artifact; Sprint 1 report ?11
A10: V15.2 | B10: Security Architecture and Dependencies | C10: V15.2.2 | D10: Verify that the application has implemented defenses against loss of availability due to functionality which is time-consuming or resource-demanding, based on the documented security decisions and strategies for this. | E10: 2 | F10: In Progress | G10: Rate limiting and file size limits reduce availability risks, but quotas/distributed controls are future work. | H10: RateLimiterService.java; FileStorageService.java
A11: V15.2 | B11: Security Architecture and Dependencies | C11: V15.2.3 | D11: Verify that the production environment only includes functionality that is required for the application to function, and does not expose extraneous functionality such as test code, sample snippets, and development functionality. | E11: 2 | F11: Not Started | G11: Production environment hardening (removal of debug/test functionality) is required but not yet formally documented. | H11: Project.pdf: backend API, 3 roles, OS/file ops, ASVS deliverable
A12: V15.2 | B12: Security Architecture and Dependencies | C12: V15.2.4 | D12: Verify that third-party components and all of their transitive dependencies are included from the expected repository, whether internally owned or an external source, and that there is no risk of a dependency confusion attack. | E12: 3 | F12: Not Started | G12: Dependency-confusion protections (e.g., private registries, namespace restrictions) are required but not yet defined. | H12: Project.pdf: backend API, 3 roles, OS/file ops, ASVS deliverable
A13: V15.2 | B13: Security Architecture and Dependencies | C13: V15.2.5 | D13: Verify that the application implements additional protections around parts of the application which are documented as containing "dangerous functionality" or using third-party libraries considered to be "risky components". This could include techniques such as sandboxing, encapsulation, containerization or network level isolation to delay and deter attackers who compromise one part of an application from pivoting elsewhere in the application. | E13: 3 | F13: In Progress | G13: High-risk file operations are isolated through generated paths, controlled directories, RBAC, and integrity controls. | H13: DESOFS Phase 1: RF2/RF7/RF8; §5.4 RS9-RS11; STRIDE T/D; §12 tests
A14: V15.3 | B14: Defensive Coding
A15: V15.3 | B15: Defensive Coding | C15: V15.3.1 | D15: Verify that the application only returns the required subset of fields from a data object. For example, it should not return an entire data object, as some individual fields should not be accessible to users. | E15: 1 | F15: Compliant | G15: Controllers return DTOs/responses rather than exposing full internal entities for main API flows. | H15: DTO package; controller package
A16: V15.3 | B16: Defensive Coding | C16: V15.3.2 | D16: Verify that where the application backend makes calls to external URLs, it is configured to not follow redirects unless it is intended functionality. | E16: 2 | F16: Not Applicable | G16: Not applicable in the current system design. | H16: N/A – not in current system scope
A17: V15.3 | B17: Defensive Coding | C17: V15.3.3 | D17: Verify that the application has countermeasures to protect against mass assignment attacks by limiting allowed fields per controller and action, e.g., it is not possible to insert or update a field value when it was not intended to be part of that action. | E17: 2 | F17: Compliant | G17: Mass assignment is mitigated through dedicated DTOs for create/update operations instead of binding request bodies directly to JPA entities. | H17: DTO package; Sprint 1 report ?5
A18: V15.3 | B18: Defensive Coding | C18: V15.3.4 | D18: Verify that all proxying and middleware components transfer the user's original IP address correctly using trusted data fields that cannot be manipulated by the end user, and the application and web server use this correct value for logging and security decisions such as rate limiting, taking into account that even the original IP address may not be reliable due to dynamic IPs, VPNs, or corporate firewalls. | E18: 2 | F18: Not Started | G18: Trusted forwarding headers and correct IP extraction logic are required but not yet specified. | H18: DESOFS Phase 1: §5.2 RS4-RS6; input validation §11; STRIDE I/P; §12 tests
A19: V15.3 | B19: Defensive Coding | C19: V15.3.5 | D19: Verify that the application explicitly ensures that variables are of the correct type and performs strict equality and comparator operations. This is to avoid type juggling or type confusion vulnerabilities caused by the application code making an assumption about a variable type. | E19: 2 | F19: In Progress | G19: Typed DTOs and Bean Validation are used, but exhaustive type enforcement review remains future work. | H19: DTO package; GlobalExceptionHandler.java
A20: V15.3 | B20: Defensive Coding | C20: V15.3.6 | D20: Verify that JavaScript code is written in a way that prevents prototype pollution, for example, by using Set() or Map() instead of object literals. | E20: 2 | F20: Not Applicable | G20: Not applicable in the current system design. | H20: N/A – not in current system scope
A21: V15.3 | B21: Defensive Coding | C21: V15.3.7 | D21: Verify that the application has defenses against HTTP parameter pollution attacks, particularly if the application framework makes no distinction about the source of request parameters (query string, body parameters, cookies, or header fields). | E21: 2 | F21: Not Started | G21: Protections against HTTP parameter pollution must be implemented but are not yet defined in the request handling logic. | H21: DESOFS Phase 1: §5.2 RS4-RS6; input validation §11; STRIDE I/P; §12 tests
A22: V15.4 | B22: Safe Concurrency
A23: V15.4 | B23: Safe Concurrency | C23: V15.4.1 | D23: Verify that shared objects in multi-threaded code (such as caches, files, or in-memory objects accessed by multiple threads) are accessed safely by using thread-safe types and synchronization mechanisms like locks or semaphores to avoid race conditions and data corruption. | E23: 3 | F23: Not Started | G23: Concurrency risks (race conditions, TOCTOU, thread safety) are identified, but specific synchronization mechanisms and safe access patterns are not yet defined. | H23: DESOFS Phase 1: RF2/RF7/RF8; §5.4 RS9-RS11; AC3/AC6/AC7; STRIDE P2/P3; §12 tests
A24: V15.4 | B24: Safe Concurrency | C24: V15.4.2 | D24: Verify that checks on a resource's state, such as its existence or permissions, and the actions that depend on them are performed as a single atomic operation to prevent time-of-check to time-of-use (TOCTOU) race conditions. For example, checking if a file exists before opening it, or verifying a user’s access before granting it. | E24: 3 | F24: Not Started | G24: Concurrency risks (race conditions, TOCTOU, thread safety) are identified, but specific synchronization mechanisms and safe access patterns are not yet defined. | H24: DESOFS Phase 1: RF2/RF7/RF8; §5.4 RS9-RS11; AC3/AC6/AC7; STRIDE P2/P3; §12 tests
A25: V15.4 | B25: Safe Concurrency | C25: V15.4.3 | D25: Verify that locks are used consistently to avoid threads getting stuck, whether by waiting on each other or retrying endlessly, and that locking logic stays within the code responsible for managing the resource to ensure locks cannot be inadvertently or maliciously modified by external classes or code. | E25: 3 | F25: Not Started | G25: Concurrency risks (race conditions, TOCTOU, thread safety) are identified, but specific synchronization mechanisms and safe access patterns are not yet defined. | H25: DESOFS Phase 1: RF2/RF7/RF8; §5.4 RS9-RS11; AC3/AC6/AC7; STRIDE P2/P3; §12 tests
A26: V15.4 | B26: Safe Concurrency | C26: V15.4.4 | D26: Verify that resource allocation policies prevent thread starvation by ensuring fair access to resources, such as by leveraging thread pools, allowing lower-priority threads to proceed within a reasonable timeframe. | E26: 3 | F26: Not Started | G26: Concurrency risks (race conditions, TOCTOU, thread safety) are identified, but specific synchronization mechanisms and safe access patterns are not yet defined. | H26: DESOFS Phase 1: RF2/RF7/RF8; §5.4 RS9-RS11; AC3/AC6/AC7; STRIDE P2/P3; §12 tests

Sheet V16 - Security Logging and Erro
A1: Section ID | B1: Section Name | C1: Req ID | D1: Description | E1: Level | F1: Status | G1: Observations | H1: Reference / Link
A2: V16.1 | B2: Security Logging Documentation
A3: V16.1 | B3: Security Logging Documentation | C3: V16.1.1 | D3: Verify that an inventory exists documenting the logging performed at each layer of the application's technology stack, what events are being logged, log formats, where that logging is stored, how it is used, how access to it is controlled, and for how long logs are kept. | E3: 2 | F3: In Progress | G3: Audit logs and security alerts are documented at application layer. Full multi-layer log inventory is not complete. | H3: AuditLogService.java; SecurityMonitoringService.java; Sprint 1 report ?9
A4: V16.2 | B4: General Logging
A5: V16.2 | B5: General Logging | C5: V16.2.1 | D5: Verify that each log entry includes necessary metadata (such as when, where, who, what) that would allow for a detailed investigation of the timeline when an event happens. | E5: 2 | F5: Compliant | G5: AuditLog stores actor, action, target type, target id, details and timestamp for critical operations. | H5: AuditLog.java; AuditLogService.java
A6: V16.2 | B6: General Logging | C6: V16.2.2 | D6: Verify that time sources for all logging components are synchronized, and that timestamps in security event metadata use UTC or include an explicit time zone offset. UTC is recommended to ensure consistency across distributed systems and to prevent confusion during daylight saving time transitions. | E6: 2 | F6: In Progress | G6: Application timestamps are recorded, but centralized clock synchronization policy is not documented. | H6: AuditLog.java; SecurityAlert.java
A7: V16.2 | B7: General Logging | C7: V16.2.3 | D7: Verify that the application only stores or broadcasts logs to the files and services that are documented in the log inventory. | E7: 2 | F7: Not Started | G7: Log destinations and allowed sinks are not yet formally defined in a logging inventory. | H7: DESOFS Phase 1: RNF4-RNF5; §5.5 RS12-RS13; AC12; STRIDE D3/P7; §12 tests
A8: V16.2 | B8: General Logging | C8: V16.2.4 | D8: Verify that logs can be read and correlated by the log processor that is in use, preferably by using a common logging format. | E8: 2 | F8: Not Started | G8: Log format standardization and correlation capability (e.g., request IDs) are not yet defined. | H8: DESOFS Phase 1: RNF4-RNF5; §5.5 RS12-RS13; AC12; STRIDE D3/P7; §12 tests
A9: V16.2 | B9: General Logging | C9: V16.2.5 | D9: Verify that when logging sensitive data, the application enforces logging based on the data's protection level. For example, it may not be allowed to log certain data, such as credentials or payment details. Other data, such as session tokens, may only be logged by being hashed or masked, either in full or partially. | E9: 2 | F9: Compliant | G9: Audit log details are sanitized and tests verify anonymous/sensitive data handling. | H9: AuditLogService.java; AnonymousDataLoggingTest
A10: V16.3 | B10: Security Events
A11: V16.3 | B11: Security Events | C11: V16.3.1 | D11: Verify that all authentication operations are logged, including successful and unsuccessful attempts. Additional metadata, such as the type of authentication or factors used, should also be collected. | E11: 2 | F11: In Progress | G11: Not all authentication events are logged in Sprint 1. Critical business/security operations are logged. | H11: AuthService.java; AuditLogService.java
A12: V16.3 | B12: Security Events | C12: V16.3.2 | D12: Verify that failed authorization attempts are logged. For L3, this must include logging all authorization decisions, including logging when sensitive data is accessed (without logging the sensitive data itself). | E12: 2 | F12: In Progress | G12: Some unauthorized backup access attempts create security alerts; complete authorization decision logging is not implemented. | H12: SecurityConfig.java; SecurityMonitoringService.java
A13: V16.3 | B13: Security Events | C13: V16.3.3 | D13: Verify that the application logs the security events that are defined in the documentation and also logs attempts to bypass the security controls, such as input validation, business logic, and anti-automation. | E13: 2 | F13: Compliant | G13: Security events such as tracking enumeration, suspicious uploads, path traversal, backup integrity failures and ownership violations are monitored. | H13: SecurityMonitoringService.java; TrackingCodeEnumerationTest; BackupServiceIntegrationTest
A14: V16.3 | B14: Security Events | C14: V16.3.4 | D14: Verify that the application logs unexpected errors and security control failures such as backend TLS failures. | E14: 2 | F14: Not Started | G14: Logging of unexpected errors and control failures is required but not yet explicitly defined. | H14: DESOFS Phase 1: RNF4-RNF5; §5.5 RS12-RS13; AC12; STRIDE D3/P7; §12 tests
A15: V16.4 | B15: Log Protection
A16: V16.4 | B16: Log Protection | C16: V16.4.1 | D16: Verify that all logging components appropriately encode data to prevent log injection. | E16: 2 | F16: Compliant | G16: Audit log details remove CR/LF/control characters to reduce log injection risk. | H16: AuditLogService.java
A17: V16.4 | B17: Log Protection | C17: V16.4.2 | D17: Verify that logs are protected from unauthorized access and cannot be modified. | E17: 2 | F17: In Progress | G17: Audit/security endpoints are protected by RBAC and included in backups, but logs are not append-only or tamper-proof. | H17: SecurityConfig.java; AuditController.java; Sprint 1 limitations
A18: V16.4 | B18: Log Protection | C18: V16.4.3 | D18: Verify that logs are securely transmitted to a logically separate system for analysis, detection, alerting, and escalation. The aim is to ensure that if the application is breached, the logs are not compromised. | E18: 2 | F18: Not Started | G18: Secure log forwarding to a separate analysis system is required but not yet defined. | H18: DESOFS Phase 1: RNF4-RNF5; §5.5 RS12-RS13; AC12; STRIDE D3/P7; §12 tests
A19: V16.5 | B19: Error Handling
A20: V16.5 | B20: Error Handling | C20: V16.5.1 | D20: Verify that a generic message is returned to the consumer when an unexpected or security-sensitive error occurs, ensuring no exposure of sensitive internal system data such as stack traces, queries, secret keys, and tokens. | E20: 2 | F20: Compliant | G20: GlobalExceptionHandler returns generic/controlled error messages and avoids stack traces in API responses. | H20: GlobalExceptionHandler.java; Sprint 1 report ?8
A21: V16.5 | B21: Error Handling | C21: V16.5.2 | D21: Verify that the application continues to operate securely when external resource access fails, for example, by using patterns such as circuit breakers or graceful degradation. | E21: 2 | F21: Not Started | G21: Resilience patterns (e.g., circuit breakers, retries, graceful degradation) are required but not yet specified. | H21: DESOFS Phase 1: RNF4-RNF5; §5.5 RS12-RS13; AC12; STRIDE D3/P7; §12 tests
A22: V16.5 | B22: Error Handling | C22: V16.5.3 | D22: Verify that the application fails gracefully and securely, including when an exception occurs, preventing fail-open conditions such as processing a transaction despite errors resulting from validation logic. | E22: 2 | F22: Compliant | G22: A centralized exception handler handles validation, access denied, missing parameters and unexpected errors safely. | H22: GlobalExceptionHandler.java
A23: V16.5 | B23: Error Handling | C23: V16.5.4 | D23: Verify that a "last resort" error handler is defined which will catch all unhandled exceptions. This is both to avoid losing error details that must go to log files and to ensure that an error does not take down the entire application process, leading to a loss of availability. | E23: 3 | F23: Compliant | G23: A catch-all Exception handler provides last-resort JSON error handling. | H23: GlobalExceptionHandler.java

Sheet V17 - WebRTC
A1: Section ID | B1: Section Name | C1: Req ID | D1: Description | E1: Level | F1: Status | G1: Observations | H1: Reference / Link
A2: V17.1 | B2: TURN Server
A3: V17.1 | B3: TURN Server | C3: V17.1.1 | D3: Verify that the Traversal Using Relays around NAT (TURN) service only allows access to IP addresses that are not reserved for special purposes (e.g., internal networks, broadcast, loopback). Note that this applies to both IPv4 and IPv6 addresses. | E3: 2 | F3: Not Applicable | G3: Not applicable – the application does not use TURN servers or NAT traversal mechanisms. | H3: DESOFS Phase 1: system scope excludes real-time communication/media services
A4: V17.1 | B4: TURN Server | C4: V17.1.2 | D4: Verify that the Traversal Using Relays around NAT (TURN) service is not susceptible to resource exhaustion when legitimate users attempt to open a large number of ports on the TURN server. | E4: 3 | F4: Not Applicable | G4: Not applicable – the application does not use TURN servers or NAT traversal mechanisms. | H4: DESOFS Phase 1: system scope excludes real-time communication/media services
A5: V17.2 | B5: Media | N5: Sprint 1 update
A6: V17.2 | B6: Media | C6: V17.2.1 | D6: Verify that the key for the Datagram Transport Layer Security (DTLS) certificate is managed and protected based on the documented policy for management of cryptographic keys. | E6: 2 | F6: Not Applicable | G6: Not applicable – the application does not process real-time audio/video media or use DTLS/SRTP protocols. | H6: DESOFS Phase 1: system scope excludes real-time communication/media services | N6: Updated from Phase 1 design tracker to reflect Sprint 1 implementation evidence, tests and DevSecOps pipeline. Open in Excel to recalculate formula-based compliance percentages.
A7: V17.2 | B7: Media | C7: V17.2.2 | D7: Verify that the media server is configured to use and support approved Datagram Transport Layer Security (DTLS) cipher suites and a secure protection profile for the DTLS Extension for establishing keys for the Secure Real-time Transport Protocol (DTLS-SRTP). | E7: 2 | F7: Not Applicable | G7: Not applicable – the application does not process real-time audio/video media or use DTLS/SRTP protocols. | H7: DESOFS Phase 1: system scope excludes real-time communication/media services
A8: V17.2 | B8: Media | C8: V17.2.3 | D8: Verify that Secure Real-time Transport Protocol (SRTP) authentication is checked at the media server to prevent Real-time Transport Protocol (RTP) injection attacks from leading to either a Denial of Service condition or audio or video media insertion into media streams. | E8: 2 | F8: Not Applicable | G8: Not applicable – the application does not process real-time audio/video media or use DTLS/SRTP protocols. | H8: DESOFS Phase 1: system scope excludes real-time communication/media services
A9: V17.2 | B9: Media | C9: V17.2.4 | D9: Verify that the media server is able to continue processing incoming media traffic when encountering malformed Secure Real-time Transport Protocol (SRTP) packets. | E9: 2 | F9: Not Applicable | G9: Not applicable – the application does not process real-time audio/video media or use DTLS/SRTP protocols. | H9: DESOFS Phase 1: system scope excludes real-time communication/media services
A10: V17.2 | B10: Media | C10: V17.2.5 | D10: Verify that the media server is able to continue processing incoming media traffic during a flood of Secure Real-time Transport Protocol (SRTP) packets from legitimate users. | E10: 3 | F10: Not Applicable | G10: Not applicable – the application does not process real-time audio/video media or use DTLS/SRTP protocols. | H10: DESOFS Phase 1: system scope excludes real-time communication/media services
A11: V17.2 | B11: Media | C11: V17.2.6 | D11: Verify that the media server is not susceptible to the "ClientHello" Race Condition vulnerability in Datagram Transport Layer Security (DTLS) by checking if the media server is publicly known to be vulnerable or by performing the race condition test. | E11: 3 | F11: Not Applicable | G11: Not applicable – the application does not process real-time audio/video media or use DTLS/SRTP protocols. | H11: DESOFS Phase 1: system scope excludes real-time communication/media services
A12: V17.2 | B12: Media | C12: V17.2.7 | D12: Verify that any audio or video recording mechanisms associated with the media server are able to continue processing incoming media traffic during a flood of Secure Real-time Transport Protocol (SRTP) packets from legitimate users. | E12: 3 | F12: Not Applicable | G12: Not applicable – the application does not process real-time audio/video media or use DTLS/SRTP protocols. | H12: DESOFS Phase 1: system scope excludes real-time communication/media services
A13: V17.2 | B13: Media | C13: V17.2.8 | D13: Verify that the Datagram Transport Layer Security (DTLS) certificate is checked against the Session Description Protocol (SDP) fingerprint attribute, terminating the media stream if the check fails, to ensure the authenticity of the media stream. | E13: 3 | F13: Not Applicable | G13: Not applicable – the application does not process real-time audio/video media or use DTLS/SRTP protocols. | H13: DESOFS Phase 1: system scope excludes real-time communication/media services
A14: V17.3 | B14: Signaling
A15: V17.3 | B15: Signaling | C15: V17.3.1 | D15: Verify that the signaling server is able to continue processing legitimate incoming signaling messages during a flood attack. This should be achieved by implementing rate limiting at the signaling level. | E15: 2 | F15: Not Applicable | G15: Not applicable – the application does not implement signaling protocols or real-time communication services. | H15: DESOFS Phase 1: system scope excludes real-time communication/media services
A16: V17.3 | B16: Signaling | C16: V17.3.2 | D16: Verify that the signaling server is able to continue processing legitimate signaling messages when encountering malformed signaling message that could cause a denial of service condition. This could include implementing input validation, safely handling integer overflows, preventing buffer overflows, and employing other robust error-handling techniques. | E16: 2 | F16: Not Applicable | G16: Not applicable – the application does not implement signaling protocols or real-time communication services. | H16: DESOFS Phase 1: system scope excludes real-time communication/media services
